[
  {
    "type": "click",
    "e": "click",
    "timestamp": "2024-08-20T00:41:17.798Z",
    "target": "BUTTON",
    "x": 719,
    "y": 19
  },
  {
    "type": "mouseMovement",
    "timestamp": "2024-08-20T00:41:17.799Z",
    "totalMouseMovement": 698.2204796752155
  },
  {
    "type": "mouseMovement",
    "timestamp": "2024-08-20T00:41:17.810Z",
    "totalMouseMovement": 699.2204796752155
  },
  {
    "type": "mouseMovement",
    "timestamp": "2024-08-20T00:41:17.857Z",
    "totalMouseMovement": 702.3827573353839
  },
  {
    "type": "mouseMovement",
    "timestamp": "2024-08-20T00:41:17.873Z",
    "totalMouseMovement": 733.3827573353839
  },
  {
    "type": "mouseMovement",
    "timestamp": "2024-08-20T00:41:17.890Z",
    "totalMouseMovement": 783.3827573353839
  },
  {
    "type": "mouseMovement",
    "timestamp": "2024-08-20T00:41:17.907Z",
    "totalMouseMovement": 862.4080697359052
  },
  {
    "type": "mouseMovement",
    "timestamp": "2024-08-20T00:41:17.923Z",
    "totalMouseMovement": 914.4176842316886
  },
  {
    "type": "idle",
    "timestamp": "2024-08-20T00:41:19.925Z",
    "duration": 2002
  },
  {
    "type": "mouseMovement",
    "timestamp": "2024-08-20T00:41:20.622Z",
    "totalMouseMovement": 915.4176842316886
  },
  {
    "type": "mouseMovement",
    "timestamp": "2024-08-20T00:41:20.638Z",
    "totalMouseMovement": 916.4176842316886
  },
  {
    "type": "mouseMovement",
    "timestamp": "2024-08-20T00:41:20.905Z",
    "totalMouseMovement": 922.2486361265338
  },
  {
    "type": "mouseMovement",
    "timestamp": "2024-08-20T00:41:20.921Z",
    "totalMouseMovement": 926.7207720815334
  },
  {
    "type": "mouseMovement",
    "timestamp": "2024-08-20T00:41:20.930Z",
    "totalMouseMovement": 930.3263233569974
  },
  {
    "type": "idle",
    "timestamp": "2024-08-20T00:41:22.944Z",
    "duration": 2013
  },
  {
    "type": "mouseMovement",
    "timestamp": "2024-08-20T00:41:25.917Z",
    "totalMouseMovement": 940.524362384183
  },
  {
    "type": "mouseMovement",
    "timestamp": "2024-08-20T00:41:25.934Z",
    "totalMouseMovement": 956.048537080443
  },
  {
    "type": "mouseMovement",
    "timestamp": "2024-08-20T00:41:25.951Z",
    "totalMouseMovement": 984.1198747756794
  },
  {
    "type": "mouseMovement",
    "timestamp": "2024-08-20T00:41:25.967Z",
    "totalMouseMovement": 1028.4030544266484
  },
  {
    "type": "mouseMovement",
    "timestamp": "2024-08-20T00:41:25.983Z",
    "totalMouseMovement": 1092.3561622479262
  },
  {
    "type": "mouseMovement",
    "timestamp": "2024-08-20T00:41:26.000Z",
    "totalMouseMovement": 1163.9243115882578
  },
  {
    "type": "mouseMovement",
    "timestamp": "2024-08-20T00:41:26.011Z",
    "totalMouseMovement": 1201.5806523557833
  },
  {
    "type": "idle",
    "timestamp": "2024-08-20T00:41:28.025Z",
    "duration": 2014
  },
  {
    "type": "mouseMovement",
    "timestamp": "2024-08-20T00:44:52.687Z",
    "totalMouseMovement": 1210.182977622826
  },
  {
    "type": "mouseMovement",
    "timestamp": "2024-08-20T00:44:52.703Z",
    "totalMouseMovement": 1229.0509398869392
  },
  {
    "type": "mouseMovement",
    "timestamp": "2024-08-20T00:44:52.720Z",
    "totalMouseMovement": 1251.7225079844484
  },
  {
    "type": "mouseMovement",
    "timestamp": "2024-08-20T00:44:52.736Z",
    "totalMouseMovement": 1278.648332020121
  },
  {
    "type": "mouseMovement",
    "timestamp": "2024-08-20T00:44:52.754Z",
    "totalMouseMovement": 1312.4861806514982
  },
  {
    "type": "mouseMovement",
    "timestamp": "2024-08-20T00:44:52.769Z",
    "totalMouseMovement": 1370.494800700591
  },
  {
    "type": "mouseMovement",
    "timestamp": "2024-08-20T00:44:52.786Z",
    "totalMouseMovement": 1411.102681709085
  },
  {
    "type": "mouseMovement",
    "timestamp": "2024-08-20T00:44:52.803Z",
    "totalMouseMovement": 1453.3045774011032
  },
  {
    "type": "mouseMovement",
    "timestamp": "2024-08-20T00:44:52.820Z",
    "totalMouseMovement": 1493.1291929045829
  },
  {
    "type": "mouseMovement",
    "timestamp": "2024-08-20T00:44:52.837Z",
    "totalMouseMovement": 1527.5384939727533
  },
  {
    "type": "mouseMovement",
    "timestamp": "2024-08-20T00:44:52.853Z",
    "totalMouseMovement": 1552.3779786695018
  },
  {
    "type": "mouseMovement",
    "timestamp": "2024-08-20T00:44:52.870Z",
    "totalMouseMovement": 1575.9788261119136
  },
  {
    "type": "mouseMovement",
    "timestamp": "2024-08-20T00:44:52.886Z",
    "totalMouseMovement": 1593.7833199266784
  },
  {
    "type": "mouseMovement",
    "timestamp": "2024-08-20T00:44:52.903Z",
    "totalMouseMovement": 1610.8127062926048
  },
  {
    "type": "mouseMovement",
    "timestamp": "2024-08-20T00:44:52.920Z",
    "totalMouseMovement": 1625.0253766961566
  },
  {
    "type": "mouseMovement",
    "timestamp": "2024-08-20T00:44:52.937Z",
    "totalMouseMovement": 1635.0253766961566
  },
  {
    "type": "mouseMovement",
    "timestamp": "2024-08-20T00:44:52.953Z",
    "totalMouseMovement": 1645.0253766961566
  },
  {
    "type": "mouseMovement",
    "timestamp": "2024-08-20T00:44:52.970Z",
    "totalMouseMovement": 1659.2380470997084
  },
  {
    "type": "mouseMovement",
    "timestamp": "2024-08-20T00:44:52.986Z",
    "totalMouseMovement": 1668.4575915570013
  },
  {
    "type": "mouseMovement",
    "timestamp": "2024-08-20T00:44:53.004Z",
    "totalMouseMovement": 1676.2678412329078
  },
  {
    "type": "mouseMovement",
    "timestamp": "2024-08-20T00:44:53.019Z",
    "totalMouseMovement": 1686.1673361695196
  },
  {
    "type": "mouseMovement",
    "timestamp": "2024-08-20T00:44:53.037Z",
    "totalMouseMovement": 1693.9775858454261
  },
  {
    "type": "mouseMovement",
    "timestamp": "2024-08-20T00:44:53.052Z",
    "totalMouseMovement": 1701.59335895129
  },
  {
    "type": "mouseMovement",
    "timestamp": "2024-08-20T00:44:53.069Z",
    "totalMouseMovement": 1707.4243108461353
  },
  {
    "type": "mouseMovement",
    "timestamp": "2024-08-20T00:44:53.086Z",
    "totalMouseMovement": 1719.6308664618691
  },
  {
    "type": "mouseMovement",
    "timestamp": "2024-08-20T00:44:53.103Z",
    "totalMouseMovement": 1731.837422077603
  },
  {
    "type": "mouseMovement",
    "timestamp": "2024-08-20T00:44:53.119Z",
    "totalMouseMovement": 1743.017761965102
  },
  {
    "type": "mouseMovement",
    "timestamp": "2024-08-20T00:44:53.138Z",
    "totalMouseMovement": 1751.0800197134006
  },
  {
    "type": "mouseMovement",
    "timestamp": "2024-08-20T00:44:53.153Z",
    "totalMouseMovement": 1761.3756498543876
  },
  {
    "type": "mouseMovement",
    "timestamp": "2024-08-20T00:44:53.169Z",
    "totalMouseMovement": 1782.2562628722087
  },
  {
    "type": "mouseMovement",
    "timestamp": "2024-08-20T00:44:53.186Z",
    "totalMouseMovement": 1788.2562628722087
  },
  {
    "type": "mouseMovement",
    "timestamp": "2024-08-20T00:44:53.203Z",
    "totalMouseMovement": 1804.2562628722087
  },
  {
    "type": "mouseMovement",
    "timestamp": "2024-08-20T00:44:53.219Z",
    "totalMouseMovement": 1825.469466307805
  },
  {
    "type": "mouseMovement",
    "timestamp": "2024-08-20T00:44:53.236Z",
    "totalMouseMovement": 1836.8712205587965
  },
  {
    "type": "mouseMovement",
    "timestamp": "2024-08-20T00:44:53.253Z",
    "totalMouseMovement": 1844.9334783070951
  },
  {
    "type": "mouseMovement",
    "timestamp": "2024-08-20T00:44:53.269Z",
    "totalMouseMovement": 1851.6416822395945
  },
  {
    "type": "mouseMovement",
    "timestamp": "2024-08-20T00:44:53.287Z",
    "totalMouseMovement": 1858.8527847905225
  },
  {
    "type": "mouseMovement",
    "timestamp": "2024-08-20T00:44:53.303Z",
    "totalMouseMovement": 1866.0638873414505
  },
  {
    "type": "mouseMovement",
    "timestamp": "2024-08-20T00:44:53.320Z",
    "totalMouseMovement": 1871.1629068550433
  },
  {
    "type": "mouseMovement",
    "timestamp": "2024-08-20T00:44:53.336Z",
    "totalMouseMovement": 1877.5660310924761
  },
  {
    "type": "mouseMovement",
    "timestamp": "2024-08-20T00:44:53.353Z",
    "totalMouseMovement": 1881.1715823679401
  },
  {
    "type": "mouseMovement",
    "timestamp": "2024-08-20T00:44:53.371Z",
    "totalMouseMovement": 1884.0000094926863
  },
  {
    "type": "mouseMovement",
    "timestamp": "2024-08-20T00:44:53.387Z",
    "totalMouseMovement": 1885.4142230550594
  },
  {
    "type": "mouseMovement",
    "timestamp": "2024-08-20T00:44:53.403Z",
    "totalMouseMovement": 1886.8284366174325
  },
  {
    "type": "mouseMovement",
    "timestamp": "2024-08-20T00:44:53.419Z",
    "totalMouseMovement": 1889.0645045949323
  },
  {
    "type": "mouseMovement",
    "timestamp": "2024-08-20T00:44:53.436Z",
    "totalMouseMovement": 1893.536640549932
  },
  {
    "type": "mouseMovement",
    "timestamp": "2024-08-20T00:44:53.453Z",
    "totalMouseMovement": 1894.536640549932
  },
  {
    "type": "mouseMovement",
    "timestamp": "2024-08-20T00:44:53.469Z",
    "totalMouseMovement": 1898.6597461755496
  },
  {
    "type": "mouseMovement",
    "timestamp": "2024-08-20T00:44:53.487Z",
    "totalMouseMovement": 1902.2652974510136
  },
  {
    "type": "mouseMovement",
    "timestamp": "2024-08-20T00:44:53.503Z",
    "totalMouseMovement": 1903.2652974510136
  },
  {
    "type": "mouseMovement",
    "timestamp": "2024-08-20T00:44:53.522Z",
    "totalMouseMovement": 1904.2652974510136
  },
  {
    "type": "mouseMovement",
    "timestamp": "2024-08-20T00:44:53.537Z",
    "totalMouseMovement": 1914.4633364781992
  },
  {
    "type": "mouseMovement",
    "timestamp": "2024-08-20T00:44:53.552Z",
    "totalMouseMovement": 1916.4633364781992
  },
  {
    "type": "mouseMovement",
    "timestamp": "2024-08-20T00:44:53.741Z",
    "totalMouseMovement": 1917.8775500405723
  },
  {
    "type": "mouseMovement",
    "timestamp": "2024-08-20T00:44:53.753Z",
    "totalMouseMovement": 1919.2917636029454
  },
  {
    "type": "mouseMovement",
    "timestamp": "2024-08-20T00:44:53.769Z",
    "totalMouseMovement": 1922.8973148784094
  },
  {
    "type": "mouseMovement",
    "timestamp": "2024-08-20T00:44:53.786Z",
    "totalMouseMovement": 1928.7282667732547
  },
  {
    "type": "mouseMovement",
    "timestamp": "2024-08-20T00:44:53.802Z",
    "totalMouseMovement": 1940.4329666839744
  },
  {
    "type": "mouseMovement",
    "timestamp": "2024-08-20T00:44:53.819Z",
    "totalMouseMovement": 1948.6791779352097
  },
  {
    "type": "mouseMovement",
    "timestamp": "2024-08-20T00:44:53.836Z",
    "totalMouseMovement": 1956.7414356835084
  },
  {
    "type": "mouseMovement",
    "timestamp": "2024-08-20T00:44:53.852Z",
    "totalMouseMovement": 1967.7867967006957
  },
  {
    "type": "mouseMovement",
    "timestamp": "2024-08-20T00:44:53.869Z",
    "totalMouseMovement": 1974.1113520210324
  },
  {
    "type": "mouseMovement",
    "timestamp": "2024-08-20T00:44:53.886Z",
    "totalMouseMovement": 1979.7682062705248
  },
  {
    "type": "mouseMovement",
    "timestamp": "2024-08-20T00:44:53.902Z",
    "totalMouseMovement": 1983.3737575459888
  },
  {
    "type": "mouseMovement",
    "timestamp": "2024-08-20T00:44:53.919Z",
    "totalMouseMovement": 1987.8458935009885
  },
  {
    "type": "mouseMovement",
    "timestamp": "2024-08-20T00:44:53.935Z",
    "totalMouseMovement": 1991.4514447764525
  },
  {
    "type": "mouseMovement",
    "timestamp": "2024-08-20T00:44:53.953Z",
    "totalMouseMovement": 1997.8545690138853
  },
  {
    "type": "mouseMovement",
    "timestamp": "2024-08-20T00:44:53.969Z",
    "totalMouseMovement": 1999.2687825762584
  },
  {
    "type": "mouseMovement",
    "timestamp": "2024-08-20T00:44:53.986Z",
    "totalMouseMovement": 2008.7027637083152
  },
  {
    "type": "mouseMovement",
    "timestamp": "2024-08-20T00:44:54.003Z",
    "totalMouseMovement": 2014.3596179578076
  },
  {
    "type": "mouseMovement",
    "timestamp": "2024-08-20T00:44:54.020Z",
    "totalMouseMovement": 2022.1698676337141
  },
  {
    "type": "mouseMovement",
    "timestamp": "2024-08-20T00:44:54.035Z",
    "totalMouseMovement": 2027.1698676337141
  },
  {
    "type": "mouseMovement",
    "timestamp": "2024-08-20T00:44:54.052Z",
    "totalMouseMovement": 2031.1698676337141
  },
  {
    "type": "mouseMovement",
    "timestamp": "2024-08-20T00:44:54.070Z",
    "totalMouseMovement": 2035.2929732593318
  },
  {
    "type": "mouseMovement",
    "timestamp": "2024-08-20T00:44:54.086Z",
    "totalMouseMovement": 2039.4160788849495
  },
  {
    "type": "mouseMovement",
    "timestamp": "2024-08-20T00:44:54.102Z",
    "totalMouseMovement": 2043.4160788849495
  },
  {
    "type": "mouseMovement",
    "timestamp": "2024-08-20T00:44:54.120Z",
    "totalMouseMovement": 2047.8882148399491
  },
  {
    "type": "mouseMovement",
    "timestamp": "2024-08-20T00:44:54.135Z",
    "totalMouseMovement": 2050.888214839949
  },
  {
    "type": "mouseMovement",
    "timestamp": "2024-08-20T00:44:54.153Z",
    "totalMouseMovement": 2056.5450690894413
  },
  {
    "type": "mouseMovement",
    "timestamp": "2024-08-20T00:44:54.169Z",
    "totalMouseMovement": 2057.5450690894413
  },
  {
    "type": "mouseMovement",
    "timestamp": "2024-08-20T00:44:54.185Z",
    "totalMouseMovement": 2061.5450690894413
  },
  {
    "type": "mouseMovement",
    "timestamp": "2024-08-20T00:44:54.202Z",
    "totalMouseMovement": 2063.781137066941
  },
  {
    "type": "mouseMovement",
    "timestamp": "2024-08-20T00:44:54.219Z",
    "totalMouseMovement": 2064.781137066941
  },
  {
    "type": "mouseMovement",
    "timestamp": "2024-08-20T00:44:54.235Z",
    "totalMouseMovement": 2065.781137066941
  },
  {
    "type": "mouseMovement",
    "timestamp": "2024-08-20T00:44:54.295Z",
    "totalMouseMovement": 2066.781137066941
  },
  {
    "type": "mouseMovement",
    "timestamp": "2024-08-20T00:44:54.302Z",
    "totalMouseMovement": 2067.781137066941
  },
  {
    "type": "mouseMovement",
    "timestamp": "2024-08-20T00:44:54.319Z",
    "totalMouseMovement": 2068.781137066941
  },
  {
    "type": "mouseMovement",
    "timestamp": "2024-08-20T00:44:54.685Z",
    "totalMouseMovement": 2069.781137066941
  },
  {
    "type": "mouseMovement",
    "timestamp": "2024-08-20T00:44:54.703Z",
    "totalMouseMovement": 2070.781137066941
  },
  {
    "type": "mouseMovement",
    "timestamp": "2024-08-20T00:44:54.719Z",
    "totalMouseMovement": 2071.781137066941
  },
  {
    "type": "mouseMovement",
    "timestamp": "2024-08-20T00:44:54.818Z",
    "totalMouseMovement": 2073.195350629314
  },
  {
    "type": "mouseMovement",
    "timestamp": "2024-08-20T00:44:54.834Z",
    "totalMouseMovement": 2076.3576282894824
  },
  {
    "type": "mouseMovement",
    "timestamp": "2024-08-20T00:44:54.851Z",
    "totalMouseMovement": 2079.963179564946
  },
  {
    "type": "mouseMovement",
    "timestamp": "2024-08-20T00:44:54.868Z",
    "totalMouseMovement": 2083.1254572251146
  },
  {
    "type": "mouseMovement",
    "timestamp": "2024-08-20T00:44:54.885Z",
    "totalMouseMovement": 2087.3680979122337
  },
  {
    "type": "mouseMovement",
    "timestamp": "2024-08-20T00:44:54.901Z",
    "totalMouseMovement": 2090.9736491876974
  },
  {
    "type": "mouseMovement",
    "timestamp": "2024-08-20T00:44:54.918Z",
    "totalMouseMovement": 2097.3767734251305
  },
  {
    "type": "mouseMovement",
    "timestamp": "2024-08-20T00:44:54.934Z",
    "totalMouseMovement": 2105.187023101037
  },
  {
    "type": "mouseMovement",
    "timestamp": "2024-08-20T00:44:54.951Z",
    "totalMouseMovement": 2115.8171689137716
  },
  {
    "type": "mouseMovement",
    "timestamp": "2024-08-20T00:44:54.968Z",
    "totalMouseMovement": 2128.855573724177
  },
  {
    "type": "mouseMovement",
    "timestamp": "2024-08-20T00:44:54.985Z",
    "totalMouseMovement": 2145.1343943202764
  },
  {
    "type": "mouseMovement",
    "timestamp": "2024-08-20T00:44:55.002Z",
    "totalMouseMovement": 2162.1049570687537
  },
  {
    "type": "mouseMovement",
    "timestamp": "2024-08-20T00:44:55.019Z",
    "totalMouseMovement": 2179.075519817231
  },
  {
    "type": "mouseMovement",
    "timestamp": "2024-08-20T00:44:55.035Z",
    "totalMouseMovement": 2196.880013631996
  },
  {
    "type": "mouseMovement",
    "timestamp": "2024-08-20T00:44:55.052Z",
    "totalMouseMovement": 2228.8956348191605
  },
  {
    "type": "mouseMovement",
    "timestamp": "2024-08-20T00:44:55.069Z",
    "totalMouseMovement": 2253.8956348191605
  },
  {
    "type": "mouseMovement",
    "timestamp": "2024-08-20T00:44:55.085Z",
    "totalMouseMovement": 2278.308746050628
  },
  {
    "type": "mouseMovement",
    "timestamp": "2024-08-20T00:44:55.102Z",
    "totalMouseMovement": 2295.5133965847135
  },
  {
    "type": "mouseMovement",
    "timestamp": "2024-08-20T00:44:55.118Z",
    "totalMouseMovement": 2315.5133965847135
  },
  {
    "type": "mouseMovement",
    "timestamp": "2024-08-20T00:44:55.135Z",
    "totalMouseMovement": 2332.718047118799
  },
  {
    "type": "mouseMovement",
    "timestamp": "2024-08-20T00:44:55.152Z",
    "totalMouseMovement": 2347.982384641273
  },
  {
    "type": "mouseMovement",
    "timestamp": "2024-08-20T00:44:55.169Z",
    "totalMouseMovement": 2361.5838551500083
  },
  {
    "type": "mouseMovement",
    "timestamp": "2024-08-20T00:44:55.186Z",
    "totalMouseMovement": 2374.6222599604134
  },
  {
    "type": "mouseMovement",
    "timestamp": "2024-08-20T00:44:55.202Z",
    "totalMouseMovement": 2386.024014211405
  },
  {
    "type": "mouseMovement",
    "timestamp": "2024-08-20T00:44:55.219Z",
    "totalMouseMovement": 2396.8406680377966
  },
  {
    "type": "mouseMovement",
    "timestamp": "2024-08-20T00:44:55.235Z",
    "totalMouseMovement": 2409.04722365353
  },
  {
    "type": "mouseMovement",
    "timestamp": "2024-08-20T00:44:55.252Z",
    "totalMouseMovement": 2424.858611954372
  },
  {
    "type": "mouseMovement",
    "timestamp": "2024-08-20T00:44:55.267Z",
    "totalMouseMovement": 2434.2925930864285
  },
  {
    "type": "mouseMovement",
    "timestamp": "2024-08-20T00:44:55.285Z",
    "totalMouseMovement": 2443.726574218485
  },
  {
    "type": "mouseMovement",
    "timestamp": "2024-08-20T00:44:55.301Z",
    "totalMouseMovement": 2452.3288994855275
  },
  {
    "type": "mouseMovement",
    "timestamp": "2024-08-20T00:44:55.318Z",
    "totalMouseMovement": 2462.6245296265147
  },
  {
    "type": "mouseMovement",
    "timestamp": "2024-08-20T00:44:55.334Z",
    "totalMouseMovement": 2472.058510758571
  },
  {
    "type": "mouseMovement",
    "timestamp": "2024-08-20T00:44:55.352Z",
    "totalMouseMovement": 2481.4924918906277
  },
  {
    "type": "mouseMovement",
    "timestamp": "2024-08-20T00:44:55.368Z",
    "totalMouseMovement": 2490.926473022684
  },
  {
    "type": "mouseMovement",
    "timestamp": "2024-08-20T00:44:55.384Z",
    "totalMouseMovement": 2495.926473022684
  },
  {
    "type": "mouseMovement",
    "timestamp": "2024-08-20T00:44:55.402Z",
    "totalMouseMovement": 2500.926473022684
  },
  {
    "type": "mouseMovement",
    "timestamp": "2024-08-20T00:44:55.419Z",
    "totalMouseMovement": 2505.926473022684
  },
  {
    "type": "mouseMovement",
    "timestamp": "2024-08-20T00:44:55.435Z",
    "totalMouseMovement": 2510.3986089776836
  },
  {
    "type": "mouseMovement",
    "timestamp": "2024-08-20T00:44:55.450Z",
    "totalMouseMovement": 2515.3986089776836
  },
  {
    "type": "mouseMovement",
    "timestamp": "2024-08-20T00:44:55.467Z",
    "totalMouseMovement": 2519.6412496648027
  },
  {
    "type": "mouseMovement",
    "timestamp": "2024-08-20T00:44:55.485Z",
    "totalMouseMovement": 2522.803527324971
  },
  {
    "type": "mouseMovement",
    "timestamp": "2024-08-20T00:44:55.501Z",
    "totalMouseMovement": 2526.409078600435
  },
  {
    "type": "mouseMovement",
    "timestamp": "2024-08-20T00:44:55.519Z",
    "totalMouseMovement": 2530.532184226053
  },
  {
    "type": "mouseMovement",
    "timestamp": "2024-08-20T00:44:55.536Z",
    "totalMouseMovement": 2535.532184226053
  },
  {
    "type": "mouseMovement",
    "timestamp": "2024-08-20T00:44:55.552Z",
    "totalMouseMovement": 2538.360611350799
  },
  {
    "type": "mouseMovement",
    "timestamp": "2024-08-20T00:44:55.568Z",
    "totalMouseMovement": 2540.5966793282987
  },
  {
    "type": "mouseMovement",
    "timestamp": "2024-08-20T00:44:55.585Z",
    "totalMouseMovement": 2545.068815283298
  },
  {
    "type": "mouseMovement",
    "timestamp": "2024-08-20T00:44:55.619Z",
    "totalMouseMovement": 2550.068815283298
  },
  {
    "type": "mouseMovement",
    "timestamp": "2024-08-20T00:44:55.635Z",
    "totalMouseMovement": 2555.8997671781435
  },
  {
    "type": "mouseMovement",
    "timestamp": "2024-08-20T00:44:55.650Z",
    "totalMouseMovement": 2568.9381719885487
  },
  {
    "type": "mouseMovement",
    "timestamp": "2024-08-20T00:44:55.667Z",
    "totalMouseMovement": 2573.410307943548
  },
  {
    "type": "mouseMovement",
    "timestamp": "2024-08-20T00:44:55.684Z",
    "totalMouseMovement": 2576.5725856037166
  },
  {
    "type": "mouseMovement",
    "timestamp": "2024-08-20T00:44:55.700Z",
    "totalMouseMovement": 2580.1781368791803
  },
  {
    "type": "mouseMovement",
    "timestamp": "2024-08-20T00:44:55.717Z",
    "totalMouseMovement": 2582.41420485668
  },
  {
    "type": "mouseMovement",
    "timestamp": "2024-08-20T00:44:55.734Z",
    "totalMouseMovement": 2584.6502728341798
  },
  {
    "type": "mouseMovement",
    "timestamp": "2024-08-20T00:44:55.750Z",
    "totalMouseMovement": 2586.8863408116795
  },
  {
    "type": "mouseMovement",
    "timestamp": "2024-08-20T00:44:55.768Z",
    "totalMouseMovement": 2588.3005543740524
  },
  {
    "type": "mouseMovement",
    "timestamp": "2024-08-20T00:44:55.802Z",
    "totalMouseMovement": 2590.3005543740524
  },
  {
    "type": "mouseMovement",
    "timestamp": "2024-08-20T00:44:55.818Z",
    "totalMouseMovement": 2591.3005543740524
  },
  {
    "type": "mouseMovement",
    "timestamp": "2024-08-20T00:44:55.835Z",
    "totalMouseMovement": 2592.7147679364252
  },
  {
    "type": "mouseMovement",
    "timestamp": "2024-08-20T00:44:55.852Z",
    "totalMouseMovement": 2594.950835913925
  },
  {
    "type": "mouseMovement",
    "timestamp": "2024-08-20T00:44:55.868Z",
    "totalMouseMovement": 2595.950835913925
  },
  {
    "type": "mouseMovement",
    "timestamp": "2024-08-20T00:44:55.885Z",
    "totalMouseMovement": 2597.365049476298
  },
  {
    "type": "mouseMovement",
    "timestamp": "2024-08-20T00:44:55.901Z",
    "totalMouseMovement": 2598.365049476298
  },
  {
    "type": "mouseMovement",
    "timestamp": "2024-08-20T00:44:55.933Z",
    "totalMouseMovement": 2600.365049476298
  },
  {
    "type": "mouseMovement",
    "timestamp": "2024-08-20T00:44:55.950Z",
    "totalMouseMovement": 2603.193476601044
  },
  {
    "type": "mouseMovement",
    "timestamp": "2024-08-20T00:44:55.968Z",
    "totalMouseMovement": 2604.193476601044
  },
  {
    "type": "mouseMovement",
    "timestamp": "2024-08-20T00:44:55.985Z",
    "totalMouseMovement": 2605.607690163417
  },
  {
    "type": "mouseMovement",
    "timestamp": "2024-08-20T00:44:56.002Z",
    "totalMouseMovement": 2607.607690163417
  },
  {
    "type": "mouseMovement",
    "timestamp": "2024-08-20T00:44:56.018Z",
    "totalMouseMovement": 2608.607690163417
  },
  {
    "type": "mouseMovement",
    "timestamp": "2024-08-20T00:44:56.035Z",
    "totalMouseMovement": 2612.2132414388807
  },
  {
    "type": "mouseMovement",
    "timestamp": "2024-08-20T00:44:56.051Z",
    "totalMouseMovement": 2615.041668563627
  },
  {
    "type": "mouseMovement",
    "timestamp": "2024-08-20T00:44:56.068Z",
    "totalMouseMovement": 2618.041668563627
  },
  {
    "type": "mouseMovement",
    "timestamp": "2024-08-20T00:44:56.084Z",
    "totalMouseMovement": 2621.6472198390907
  },
  {
    "type": "mouseMovement",
    "timestamp": "2024-08-20T00:44:56.117Z",
    "totalMouseMovement": 2622.6472198390907
  },
  {
    "type": "mouseMovement",
    "timestamp": "2024-08-20T00:44:56.151Z",
    "totalMouseMovement": 2624.0614334014635
  },
  {
    "type": "mouseMovement",
    "timestamp": "2024-08-20T00:44:56.201Z",
    "totalMouseMovement": 2625.0614334014635
  },
  {
    "type": "mouseMovement",
    "timestamp": "2024-08-20T00:44:56.234Z",
    "totalMouseMovement": 2626.0614334014635
  },
  {
    "type": "mouseMovement",
    "timestamp": "2024-08-20T00:44:56.251Z",
    "totalMouseMovement": 2627.0614334014635
  },
  {
    "type": "mouseMovement",
    "timestamp": "2024-08-20T00:44:56.267Z",
    "totalMouseMovement": 2628.0614334014635
  },
  {
    "type": "mouseMovement",
    "timestamp": "2024-08-20T00:44:56.284Z",
    "totalMouseMovement": 2629.4756469638364
  },
  {
    "type": "mouseMovement",
    "timestamp": "2024-08-20T00:44:56.301Z",
    "totalMouseMovement": 2630.8898605262093
  },
  {
    "type": "mouseMovement",
    "timestamp": "2024-08-20T00:44:56.318Z",
    "totalMouseMovement": 2632.8898605262093
  },
  {
    "type": "mouseMovement",
    "timestamp": "2024-08-20T00:44:56.351Z",
    "totalMouseMovement": 2633.8898605262093
  },
  {
    "type": "mouseMovement",
    "timestamp": "2024-08-20T00:44:56.367Z",
    "totalMouseMovement": 2634.8898605262093
  },
  {
    "type": "mouseMovement",
    "timestamp": "2024-08-20T00:44:56.383Z",
    "totalMouseMovement": 2637.125928503709
  },
  {
    "type": "mouseMovement",
    "timestamp": "2024-08-20T00:44:56.400Z",
    "totalMouseMovement": 2638.540142066082
  },
  {
    "type": "mouseMovement",
    "timestamp": "2024-08-20T00:44:56.416Z",
    "totalMouseMovement": 2640.540142066082
  },
  {
    "type": "mouseMovement",
    "timestamp": "2024-08-20T00:44:56.434Z",
    "totalMouseMovement": 2641.540142066082
  },
  {
    "type": "mouseMovement",
    "timestamp": "2024-08-20T00:44:56.451Z",
    "totalMouseMovement": 2643.540142066082
  },
  {
    "type": "mouseMovement",
    "timestamp": "2024-08-20T00:44:56.467Z",
    "totalMouseMovement": 2645.540142066082
  },
  {
    "type": "mouseMovement",
    "timestamp": "2024-08-20T00:44:56.483Z",
    "totalMouseMovement": 2648.368569190828
  },
  {
    "type": "mouseMovement",
    "timestamp": "2024-08-20T00:44:56.500Z",
    "totalMouseMovement": 2650.368569190828
  },
  {
    "type": "mouseMovement",
    "timestamp": "2024-08-20T00:44:56.518Z",
    "totalMouseMovement": 2651.368569190828
  },
  {
    "type": "mouseMovement",
    "timestamp": "2024-08-20T00:44:56.533Z",
    "totalMouseMovement": 2652.782782753201
  },
  {
    "type": "mouseMovement",
    "timestamp": "2024-08-20T00:44:56.551Z",
    "totalMouseMovement": 2653.782782753201
  },
  {
    "type": "mouseMovement",
    "timestamp": "2024-08-20T00:44:56.567Z",
    "totalMouseMovement": 2655.196996315574
  },
  {
    "type": "mouseMovement",
    "timestamp": "2024-08-20T00:44:56.601Z",
    "totalMouseMovement": 2657.196996315574
  },
  {
    "type": "mouseMovement",
    "timestamp": "2024-08-20T00:44:56.634Z",
    "totalMouseMovement": 2658.196996315574
  },
  {
    "type": "mouseMovement",
    "timestamp": "2024-08-20T00:44:56.651Z",
    "totalMouseMovement": 2659.6112098779467
  },
  {
    "type": "mouseMovement",
    "timestamp": "2024-08-20T00:44:56.700Z",
    "totalMouseMovement": 2661.6112098779467
  },
  {
    "type": "mouseMovement",
    "timestamp": "2024-08-20T00:44:56.734Z",
    "totalMouseMovement": 2663.0254234403196
  },
  {
    "type": "mouseMovement",
    "timestamp": "2024-08-20T00:44:56.751Z",
    "totalMouseMovement": 2664.0254234403196
  },
  {
    "type": "mouseMovement",
    "timestamp": "2024-08-20T00:44:56.802Z",
    "totalMouseMovement": 2665.0254234403196
  },
  {
    "type": "mouseMovement",
    "timestamp": "2024-08-20T00:44:56.818Z",
    "totalMouseMovement": 2666.0254234403196
  },
  {
    "type": "mouseMovement",
    "timestamp": "2024-08-20T00:44:56.834Z",
    "totalMouseMovement": 2667.4396370026925
  },
  {
    "type": "mouseMovement",
    "timestamp": "2024-08-20T00:44:56.851Z",
    "totalMouseMovement": 2668.4396370026925
  },
  {
    "type": "mouseMovement",
    "timestamp": "2024-08-20T00:44:56.901Z",
    "totalMouseMovement": 2669.8538505650654
  },
  {
    "type": "mouseMovement",
    "timestamp": "2024-08-20T00:44:57.467Z",
    "totalMouseMovement": 2670.8538505650654
  },
  {
    "type": "mouseMovement",
    "timestamp": "2024-08-20T00:44:57.484Z",
    "totalMouseMovement": 2671.8538505650654
  },
  {
    "type": "mouseMovement",
    "timestamp": "2024-08-20T00:44:57.500Z",
    "totalMouseMovement": 2673.8538505650654
  },
  {
    "type": "mouseMovement",
    "timestamp": "2024-08-20T00:44:57.516Z",
    "totalMouseMovement": 2675.8538505650654
  },
  {
    "type": "mouseMovement",
    "timestamp": "2024-08-20T00:44:57.533Z",
    "totalMouseMovement": 2677.8538505650654
  },
  {
    "type": "mouseMovement",
    "timestamp": "2024-08-20T00:44:57.550Z",
    "totalMouseMovement": 2680.8538505650654
  },
  {
    "type": "mouseMovement",
    "timestamp": "2024-08-20T00:44:57.566Z",
    "totalMouseMovement": 2682.8538505650654
  },
  {
    "type": "mouseMovement",
    "timestamp": "2024-08-20T00:44:57.582Z",
    "totalMouseMovement": 2683.8538505650654
  },
  {
    "type": "mouseMovement",
    "timestamp": "2024-08-20T00:44:57.599Z",
    "totalMouseMovement": 2685.8538505650654
  },
  {
    "type": "mouseMovement",
    "timestamp": "2024-08-20T00:44:57.616Z",
    "totalMouseMovement": 2686.8538505650654
  },
  {
    "type": "mouseMovement",
    "timestamp": "2024-08-20T00:44:57.632Z",
    "totalMouseMovement": 2688.8538505650654
  },
  {
    "type": "mouseMovement",
    "timestamp": "2024-08-20T00:44:57.649Z",
    "totalMouseMovement": 2690.2680641274383
  },
  {
    "type": "mouseMovement",
    "timestamp": "2024-08-20T00:44:57.665Z",
    "totalMouseMovement": 2691.2680641274383
  },
  {
    "type": "mouseMovement",
    "timestamp": "2024-08-20T00:44:57.682Z",
    "totalMouseMovement": 2693.504132104938
  },
  {
    "type": "mouseMovement",
    "timestamp": "2024-08-20T00:44:57.699Z",
    "totalMouseMovement": 2695.504132104938
  },
  {
    "type": "mouseMovement",
    "timestamp": "2024-08-20T00:44:57.716Z",
    "totalMouseMovement": 2699.9762680599374
  },
  {
    "type": "mouseMovement",
    "timestamp": "2024-08-20T00:44:57.732Z",
    "totalMouseMovement": 2703.9762680599374
  },
  {
    "type": "mouseMovement",
    "timestamp": "2024-08-20T00:44:57.749Z",
    "totalMouseMovement": 2708.0993736855553
  },
  {
    "type": "mouseMovement",
    "timestamp": "2024-08-20T00:44:57.766Z",
    "totalMouseMovement": 2713.9303255804007
  },
  {
    "type": "mouseMovement",
    "timestamp": "2024-08-20T00:44:57.782Z",
    "totalMouseMovement": 2721.1414281313287
  },
  {
    "type": "mouseMovement",
    "timestamp": "2024-08-20T00:44:57.799Z",
    "totalMouseMovement": 2729.743753398371
  },
  {
    "type": "mouseMovement",
    "timestamp": "2024-08-20T00:44:57.815Z",
    "totalMouseMovement": 2739.743753398371
  },
  {
    "type": "mouseMovement",
    "timestamp": "2024-08-20T00:44:57.832Z",
    "totalMouseMovement": 2745.5747052932165
  },
  {
    "type": "mouseMovement",
    "timestamp": "2024-08-20T00:44:57.849Z",
    "totalMouseMovement": 2751.9778295306496
  },
  {
    "type": "mouseMovement",
    "timestamp": "2024-08-20T00:44:57.866Z",
    "totalMouseMovement": 2754.2138975081493
  },
  {
    "type": "mouseMovement",
    "timestamp": "2024-08-20T00:44:57.882Z",
    "totalMouseMovement": 2756.449965485649
  },
  {
    "type": "mouseMovement",
    "timestamp": "2024-08-20T00:44:57.899Z",
    "totalMouseMovement": 2757.864179048022
  },
  {
    "type": "highlight",
    "timestamp": "2024-08-20T00:44:58.268Z",
    "highlightedText": "Task1:  Collaborate with GPT: Survival in the Desert\nIt is approximately 10:00 am in mid-July and you have just crash landed in the Atacama Desert in South America. Your light twin-engined plane containing the bodies of the pilot and co-pilot has completely burned out with only the frame remaining. None of you have been injured. The pilot was unable to notify anyone of your position before the crash. However, he had indicated before impact that you were 50 miles from a mining camp, which is the nearest known settlement, and approximately 65 miles off the course that was filed in your Flight Plan. The immediate area is quite flat, except for occasional cacti, and appears to be rather barren. The last weather report indicated that the temperature would reach 110 F today, which means that the temperature at ground level will be 130 F. You are dressed in lightweight clothing-short-sleeved shirts, pants, socks, and street shoes. Everyone has a handkerchief and collectively, you have 3 packs of cigarettes and a ballpoint pen. Before your plane caught fire, your group was able to salvage the 15 items listed on the “Salvaged Items” page. Your task is to rank these items according to their importance to your survival, starting with a “1” for the most important,to a “15” for the least important.\n\nNotice:\nwhat you need to know before you can begin creating a list of essential items? The list of items is dependent upon the location and conditions of the new world.\n\nYour items:\nTorch with 4 battery-cells\nFolding knife\nAir map of the area\nPlastic raincoat (large size)\nMagnetic compass\nFirst-aid kit\n45 calibre pistol (loaded)\nParachute (red & white)\nBottle of 1000 salt tablets\n2 litres of water per person\nA book entitled ‘Desert Animals That Can Be Eaten’\nSunglasses (for everyone)\n2 litres of 180 proof liquor\nOvercoat (for everyone)\nA cosmetic mirror",
    "highlightedTextLength": 1867
  },
  {
    "type": "click",
    "e": "click",
    "timestamp": "2024-08-20T00:44:58.269Z",
    "target": "DIV",
    "x": 383,
    "y": 653
  },
  {
    "type": "mouseMovement",
    "timestamp": "2024-08-20T00:44:58.466Z",
    "totalMouseMovement": 2758.864179048022
  },
  {
    "type": "mouseMovement",
    "timestamp": "2024-08-20T00:44:58.482Z",
    "totalMouseMovement": 2759.864179048022
  },
  {
    "type": "mouseMovement",
    "timestamp": "2024-08-20T00:44:58.498Z",
    "totalMouseMovement": 2768.1103902992572
  },
  {
    "type": "mouseMovement",
    "timestamp": "2024-08-20T00:44:58.515Z",
    "totalMouseMovement": 2778.308429326443
  },
  {
    "type": "mouseMovement",
    "timestamp": "2024-08-20T00:44:58.531Z",
    "totalMouseMovement": 2796.4191996027175
  },
  {
    "type": "mouseMovement",
    "timestamp": "2024-08-20T00:44:58.548Z",
    "totalMouseMovement": 2820.4191996027175
  },
  {
    "type": "mouseMovement",
    "timestamp": "2024-08-20T00:44:58.556Z",
    "totalMouseMovement": 2833.5721460406835
  },
  {
    "type": "copy",
    "timestamp": "2024-08-20T00:44:58.557Z",
    "text": "Task1:  Collaborate with GPT: Survival in the Desert\nIt is approximately 10:00 am in mid-July and you have just crash landed in the Atacama Desert in South America. Your light twin-engined plane containing the bodies of the pilot and co-pilot has completely burned out with only the frame remaining. None of you have been injured. The pilot was unable to notify anyone of your position before the crash. However, he had indicated before impact that you were 50 miles from a mining camp, which is the nearest known settlement, and approximately 65 miles off the course that was filed in your Flight Plan. The immediate area is quite flat, except for occasional cacti, and appears to be rather barren. The last weather report indicated that the temperature would reach 110 F today, which means that the temperature at ground level will be 130 F. You are dressed in lightweight clothing-short-sleeved shirts, pants, socks, and street shoes. Everyone has a handkerchief and collectively, you have 3 packs of cigarettes and a ballpoint pen. Before your plane caught fire, your group was able to salvage the 15 items listed on the “Salvaged Items” page. Your task is to rank these items according to their importance to your survival, starting with a “1” for the most important,to a “15” for the least important.\n\nNotice:\nwhat you need to know before you can begin creating a list of essential items? The list of items is dependent upon the location and conditions of the new world.\n\nYour items:\nTorch with 4 battery-cells\nFolding knife\nAir map of the area\nPlastic raincoat (large size)\nMagnetic compass\nFirst-aid kit\n45 calibre pistol (loaded)\nParachute (red & white)\nBottle of 1000 salt tablets\n2 litres of water per person\nA book entitled ‘Desert Animals That Can Be Eaten’\nSunglasses (for everyone)\n2 litres of 180 proof liquor\nOvercoat (for everyone)\nA cosmetic mirror",
    "textLength": 1867
  },
  {
    "type": "mouseMovement",
    "timestamp": "2024-08-20T00:44:58.565Z",
    "totalMouseMovement": 2846.5721460406835
  },
  {
    "type": "mouseMovement",
    "timestamp": "2024-08-20T00:44:58.581Z",
    "totalMouseMovement": 2876.5721460406835
  },
  {
    "type": "mouseMovement",
    "timestamp": "2024-08-20T00:44:58.598Z",
    "totalMouseMovement": 2909.587294079122
  },
  {
    "type": "mouseMovement",
    "timestamp": "2024-08-20T00:44:58.615Z",
    "totalMouseMovement": 2942.587294079122
  },
  {
    "type": "mouseMovement",
    "timestamp": "2024-08-20T00:44:58.632Z",
    "totalMouseMovement": 2980.6004496966184
  },
  {
    "type": "mouseMovement",
    "timestamp": "2024-08-20T00:44:58.648Z",
    "totalMouseMovement": 3027.6004496966184
  },
  {
    "type": "mouseMovement",
    "timestamp": "2024-08-20T00:44:58.665Z",
    "totalMouseMovement": 3102.6004496966184
  },
  {
    "type": "mouseMovement",
    "timestamp": "2024-08-20T00:44:58.682Z",
    "totalMouseMovement": 3125.6872424578487
  },
  {
    "type": "idle",
    "timestamp": "2024-08-20T00:45:00.697Z",
    "duration": 2015
  },
  {
    "type": "mouseMovement",
    "timestamp": "2024-08-20T00:45:44.180Z",
    "totalMouseMovement": 3127.1014560202216
  },
  {
    "type": "highlight",
    "timestamp": "2024-08-20T00:45:44.226Z",
    "highlightedText": "Task1:  Collaborate with GPT: Survival in the Desert\nIt is approximately 10:00 am in mid-July and you have just crash landed in the Atacama Desert in South America. Your light twin-engined plane containing the bodies of the pilot and co-pilot has completely burned out with only the frame remaining. None of you have been injured. The pilot was unable to notify anyone of your position before the crash. However, he had indicated before impact that you were 50 miles from a mining camp, which is the nearest known settlement, and approximately 65 miles off the course that was filed in your Flight Plan. The immediate area is quite flat, except for occasional cacti, and appears to be rather barren. The last weather report indicated that the temperature would reach 110 F today, which means that the temperature at ground level will be 130 F. You are dressed in lightweight clothing-short-sleeved shirts, pants, socks, and street shoes. Everyone has a handkerchief and collectively, you have 3 packs of cigarettes and a ballpoint pen. Before your plane caught fire, your group was able to salvage the 15 items listed on the “Salvaged Items” page. Your task is to rank these items according to their importance to your survival, starting with a “1” for the most important,to a “15” for the least important.\n\nNotice:\nwhat you need to know before you can begin creating a list of essential items? The list of items is dependent upon the location and conditions of the new world.\n\nYour items:\nTorch with 4 battery-cells\nFolding knife\nAir map of the area\nPlastic raincoat (large size)\nMagnetic compass\nFirst-aid kit\n45 calibre pistol (loaded)\nParachute (red & white)\nBottle of 1000 salt tablets\n2 litres of water per person\nA book entitled ‘Desert Animals That Can Be Eaten’\nSunglasses (for everyone)\n2 litres of 180 proof liquor\nOvercoat (for everyone)\nA cosmetic mirror",
    "highlightedTextLength": 1867
  },
  {
    "type": "click",
    "e": "click",
    "timestamp": "2024-08-20T00:45:44.229Z",
    "target": "LI",
    "x": 604,
    "y": 470
  },
  {
    "type": "mouseMovement",
    "timestamp": "2024-08-20T00:45:44.717Z",
    "totalMouseMovement": 3128.1014560202216
  },
  {
    "type": "mouseMovement",
    "timestamp": "2024-08-20T00:45:44.726Z",
    "totalMouseMovement": 3131.1014560202216
  },
  {
    "type": "mouseMovement",
    "timestamp": "2024-08-20T00:45:44.743Z",
    "totalMouseMovement": 3135.2245616458395
  },
  {
    "type": "mouseMovement",
    "timestamp": "2024-08-20T00:45:44.759Z",
    "totalMouseMovement": 3144.7113946263444
  },
  {
    "type": "mouseMovement",
    "timestamp": "2024-08-20T00:45:44.776Z",
    "totalMouseMovement": 3153.313719893387
  },
  {
    "type": "mouseMovement",
    "timestamp": "2024-08-20T00:45:44.793Z",
    "totalMouseMovement": 3163.162577695183
  },
  {
    "type": "mouseMovement",
    "timestamp": "2024-08-20T00:45:44.809Z",
    "totalMouseMovement": 3172.5965588272393
  },
  {
    "type": "mouseMovement",
    "timestamp": "2024-08-20T00:45:44.825Z",
    "totalMouseMovement": 3181.140562572557
  },
  {
    "type": "mouseMovement",
    "timestamp": "2024-08-20T00:45:44.842Z",
    "totalMouseMovement": 3187.5436868099896
  },
  {
    "type": "mouseMovement",
    "timestamp": "2024-08-20T00:45:44.858Z",
    "totalMouseMovement": 3195.1594599158534
  },
  {
    "type": "mouseMovement",
    "timestamp": "2024-08-20T00:45:44.875Z",
    "totalMouseMovement": 3202.2305277277187
  },
  {
    "type": "highlight",
    "timestamp": "2024-08-20T00:45:44.990Z",
    "highlightedText": "Task1:  Collaborate with GPT: Survival in the Desert\nIt is approximately 10:00 am in mid-July and you have just crash landed in the Atacama Desert in South America. Your light twin-engined plane containing the bodies of the pilot and co-pilot has completely burned out with only the frame remaining. None of you have been injured. The pilot was unable to notify anyone of your position before the crash. However, he had indicated before impact that you were 50 miles from a mining camp, which is the nearest known settlement, and approximately 65 miles off the course that was filed in your Flight Plan. The immediate area is quite flat, except for occasional cacti, and appears to be rather barren. The last weather report indicated that the temperature would reach 110 F today, which means that the temperature at ground level will be 130 F. You are dressed in lightweight clothing-short-sleeved shirts, pants, socks, and street shoes. Everyone has a handkerchief and collectively, you have 3 packs of cigarettes and a ballpoint pen. Before your plane caught fire, your group was able to salvage the 15 items listed on the “Salvaged Items” page. Your task is to rank these items according to their importance to your survival, starting with a “1” for the most important,to a “15” for the least important.\n\nNotice:\nwhat you need to know before you can begin creating a list of essential items? The list of items is dependent upon the location and conditions of the new world.\n\nYour items:\nTorch with 4 battery-cells\nFolding knife\nAir map of the area\nPlastic raincoat (large size)\nMagnetic compass\nFirst-aid kit\n45 calibre pistol (loaded)\nParachute (red & white)\nBottle of 1000 salt tablets\n2 litres of water per person\nA book entitled ‘Desert Animals That Can Be Eaten’\nSunglasses (for everyone)\n2 litres of 180 proof liquor\nOvercoat (for everyone)\nA cosmetic mirror",
    "highlightedTextLength": 1867
  },
  {
    "type": "click",
    "e": "click",
    "timestamp": "2024-08-20T00:45:44.993Z",
    "target": "DIV",
    "x": 672,
    "y": 441
  },
  {
    "type": "mousewheel",
    "timestamp": "2024-08-20T00:45:45.583Z",
    "deltaY": 100
  },
  {
    "type": "mousewheel",
    "timestamp": "2024-08-20T00:45:45.608Z",
    "deltaY": 100
  },
  {
    "type": "mousewheel",
    "timestamp": "2024-08-20T00:45:45.658Z",
    "deltaY": 100
  },
  {
    "type": "mousewheel",
    "timestamp": "2024-08-20T00:45:45.964Z",
    "deltaY": 100
  },
  {
    "type": "mousewheel",
    "timestamp": "2024-08-20T00:45:46.024Z",
    "deltaY": 100
  },
  {
    "type": "scroll",
    "timestamp": "2024-08-20T00:45:46.525Z",
    "deltaY": 100
  },
  {
    "type": "mousewheel",
    "timestamp": "2024-08-20T00:45:46.557Z",
    "deltaY": 100
  },
  {
    "type": "mousewheel",
    "timestamp": "2024-08-20T00:45:46.607Z",
    "deltaY": 100
  },
  {
    "type": "scroll",
    "timestamp": "2024-08-20T00:45:47.118Z",
    "deltaY": 100
  },
  {
    "type": "mouseMovement",
    "timestamp": "2024-08-20T00:45:47.430Z",
    "totalMouseMovement": 3203.2305277277187
  },
  {
    "type": "mouseMovement",
    "timestamp": "2024-08-20T00:45:47.439Z",
    "totalMouseMovement": 3204.2305277277187
  },
  {
    "type": "mouseMovement",
    "timestamp": "2024-08-20T00:45:47.456Z",
    "totalMouseMovement": 3226.3212497620934
  },
  {
    "type": "mouseMovement",
    "timestamp": "2024-08-20T00:45:47.473Z",
    "totalMouseMovement": 3263.3212497620934
  },
  {
    "type": "mouseMovement",
    "timestamp": "2024-08-20T00:45:47.484Z",
    "totalMouseMovement": 3284.3212497620934
  },
  {
    "type": "idle",
    "timestamp": "2024-08-20T00:45:49.486Z",
    "duration": 2002
  },
  {
    "type": "mouseMovement",
    "timestamp": "2024-08-20T00:46:09.237Z",
    "totalMouseMovement": 3290.7243739995265
  },
  {
    "type": "mouseMovement",
    "timestamp": "2024-08-20T00:46:09.254Z",
    "totalMouseMovement": 3303.254338085668
  },
  {
    "type": "mouseMovement",
    "timestamp": "2024-08-20T00:46:09.271Z",
    "totalMouseMovement": 3308.254338085668
  },
  {
    "type": "mouseMovement",
    "timestamp": "2024-08-20T00:46:09.288Z",
    "totalMouseMovement": 3316.316595833967
  },
  {
    "type": "mouseMovement",
    "timestamp": "2024-08-20T00:46:09.304Z",
    "totalMouseMovement": 3322.1475477288122
  },
  {
    "type": "mouseMovement",
    "timestamp": "2024-08-20T00:46:09.338Z",
    "totalMouseMovement": 3323.561761291185
  },
  {
    "type": "idle",
    "timestamp": "2024-08-20T00:46:12.202Z",
    "duration": 2014
  },
  {
    "type": "mouseMovement",
    "timestamp": "2024-08-20T00:46:34.159Z",
    "totalMouseMovement": 3739.638677257452
  },
  {
    "type": "mouseMovement",
    "timestamp": "2024-08-20T00:46:34.166Z",
    "totalMouseMovement": 3757.6664336347717
  },
  {
    "type": "mouseMovement",
    "timestamp": "2024-08-20T00:46:34.183Z",
    "totalMouseMovement": 3792.6521450038435
  },
  {
    "type": "mouseMovement",
    "timestamp": "2024-08-20T00:46:34.200Z",
    "totalMouseMovement": 3817.2488927563413
  },
  {
    "type": "mouseMovement",
    "timestamp": "2024-08-20T00:46:34.215Z",
    "totalMouseMovement": 3832.013715816575
  },
  {
    "type": "mouseMovement",
    "timestamp": "2024-08-20T00:46:34.232Z",
    "totalMouseMovement": 3839.224818367503
  },
  {
    "type": "mouseMovement",
    "timestamp": "2024-08-20T00:46:34.250Z",
    "totalMouseMovement": 3841.4608863450026
  },
  {
    "type": "mouseMovement",
    "timestamp": "2024-08-20T00:46:34.265Z",
    "totalMouseMovement": 3843.4608863450026
  },
  {
    "type": "mouseMovement",
    "timestamp": "2024-08-20T00:46:34.283Z",
    "totalMouseMovement": 3845.4608863450026
  },
  {
    "type": "mouseMovement",
    "timestamp": "2024-08-20T00:46:34.301Z",
    "totalMouseMovement": 3847.4608863450026
  },
  {
    "type": "mouseMovement",
    "timestamp": "2024-08-20T00:46:34.316Z",
    "totalMouseMovement": 3848.4608863450026
  },
  {
    "type": "mouseMovement",
    "timestamp": "2024-08-20T00:46:34.635Z",
    "totalMouseMovement": 3856.523144093301
  },
  {
    "type": "mouseMovement",
    "timestamp": "2024-08-20T00:46:34.648Z",
    "totalMouseMovement": 3865.523144093301
  },
  {
    "type": "mouseMovement",
    "timestamp": "2024-08-20T00:46:34.665Z",
    "totalMouseMovement": 3890.0384454375635
  },
  {
    "type": "mouseMovement",
    "timestamp": "2024-08-20T00:46:34.681Z",
    "totalMouseMovement": 3918.1097831327997
  },
  {
    "type": "mouseMovement",
    "timestamp": "2024-08-20T00:46:34.698Z",
    "totalMouseMovement": 3962.2912272015487
  },
  {
    "type": "mouseMovement",
    "timestamp": "2024-08-20T00:46:34.715Z",
    "totalMouseMovement": 3995.351777711182
  },
  {
    "type": "mouseMovement",
    "timestamp": "2024-08-20T00:46:34.731Z",
    "totalMouseMovement": 4025.351777711182
  },
  {
    "type": "mouseMovement",
    "timestamp": "2024-08-20T00:46:34.747Z",
    "totalMouseMovement": 4038.504724149148
  },
  {
    "type": "idle",
    "timestamp": "2024-08-20T00:46:36.758Z",
    "duration": 2011
  },
  {
    "type": "mouseMovement",
    "timestamp": "2024-08-20T00:47:25.154Z",
    "totalMouseMovement": 4070.332385074827
  },
  {
    "type": "mouseMovement",
    "timestamp": "2024-08-20T00:47:25.171Z",
    "totalMouseMovement": 4103.93298030765
  },
  {
    "type": "mouseMovement",
    "timestamp": "2024-08-20T00:47:25.188Z",
    "totalMouseMovement": 4184.7413957109975
  },
  {
    "type": "mouseMovement",
    "timestamp": "2024-08-20T00:47:25.205Z",
    "totalMouseMovement": 4284.099334497992
  },
  {
    "type": "mouseMovement",
    "timestamp": "2024-08-20T00:47:25.223Z",
    "totalMouseMovement": 4431.727245138222
  },
  {
    "type": "mouseMovement",
    "timestamp": "2024-08-20T00:47:25.239Z",
    "totalMouseMovement": 4515.135877784969
  },
  {
    "type": "mouseMovement",
    "timestamp": "2024-08-20T00:47:25.256Z",
    "totalMouseMovement": 4548.973726416347
  },
  {
    "type": "mouseMovement",
    "timestamp": "2024-08-20T00:47:25.271Z",
    "totalMouseMovement": 4594.250652107034
  },
  {
    "type": "mouseMovement",
    "timestamp": "2024-08-20T00:47:25.288Z",
    "totalMouseMovement": 4598.493292794153
  },
  {
    "type": "mouseMovement",
    "timestamp": "2024-08-20T00:47:25.305Z",
    "totalMouseMovement": 4599.493292794153
  },
  {
    "type": "mouseMovement",
    "timestamp": "2024-08-20T00:47:25.467Z",
    "totalMouseMovement": 4601.493292794153
  },
  {
    "type": "mouseMovement",
    "timestamp": "2024-08-20T00:47:25.470Z",
    "totalMouseMovement": 4602.493292794153
  },
  {
    "type": "mouseMovement",
    "timestamp": "2024-08-20T00:47:25.487Z",
    "totalMouseMovement": 4605.321719918898
  },
  {
    "type": "mouseMovement",
    "timestamp": "2024-08-20T00:47:25.505Z",
    "totalMouseMovement": 4608.927271194362
  },
  {
    "type": "mouseMovement",
    "timestamp": "2024-08-20T00:47:25.521Z",
    "totalMouseMovement": 4610.341484756736
  },
  {
    "type": "mouseMovement",
    "timestamp": "2024-08-20T00:47:25.538Z",
    "totalMouseMovement": 4611.341484756736
  },
  {
    "type": "mouseMovement",
    "timestamp": "2024-08-20T00:47:25.571Z",
    "totalMouseMovement": 4612.341484756736
  },
  {
    "type": "mouseMovement",
    "timestamp": "2024-08-20T00:47:25.588Z",
    "totalMouseMovement": 4614.341484756736
  },
  {
    "type": "mouseMovement",
    "timestamp": "2024-08-20T00:47:25.605Z",
    "totalMouseMovement": 4615.341484756736
  },
  {
    "type": "mouseMovement",
    "timestamp": "2024-08-20T00:47:25.670Z",
    "totalMouseMovement": 4616.341484756736
  },
  {
    "type": "idle",
    "timestamp": "2024-08-20T00:47:27.674Z",
    "duration": 2003
  },
  {
    "type": "mousewheel",
    "timestamp": "2024-08-20T00:47:28.599Z",
    "deltaY": 100
  },
  {
    "type": "mousewheel",
    "timestamp": "2024-08-20T00:47:28.651Z",
    "deltaY": 100
  },
  {
    "type": "mousewheel",
    "timestamp": "2024-08-20T00:47:29.114Z",
    "deltaY": 100
  },
  {
    "type": "mousewheel",
    "timestamp": "2024-08-20T00:47:29.184Z",
    "deltaY": 100
  },
  {
    "type": "mousewheel",
    "timestamp": "2024-08-20T00:47:29.667Z",
    "deltaY": -100
  },
  {
    "type": "mousewheel",
    "timestamp": "2024-08-20T00:47:29.701Z",
    "deltaY": -100
  },
  {
    "type": "scroll",
    "timestamp": "2024-08-20T00:47:30.201Z",
    "deltaY": -100
  },
  {
    "type": "mousewheel",
    "timestamp": "2024-08-20T00:47:30.273Z",
    "deltaY": -100
  },
  {
    "type": "mousewheel",
    "timestamp": "2024-08-20T00:47:30.300Z",
    "deltaY": -100
  },
  {
    "type": "mousewheel",
    "timestamp": "2024-08-20T00:47:30.351Z",
    "deltaY": -100
  },
  {
    "type": "scroll",
    "timestamp": "2024-08-20T00:47:30.851Z",
    "deltaY": -100
  },
  {
    "type": "mouseMovement",
    "timestamp": "2024-08-20T00:47:30.927Z",
    "totalMouseMovement": 4619.341484756736
  },
  {
    "type": "mouseMovement",
    "timestamp": "2024-08-20T00:47:30.933Z",
    "totalMouseMovement": 4625.424247287034
  },
  {
    "type": "mouseMovement",
    "timestamp": "2024-08-20T00:47:30.950Z",
    "totalMouseMovement": 4640.457543665407
  },
  {
    "type": "mouseMovement",
    "timestamp": "2024-08-20T00:47:30.967Z",
    "totalMouseMovement": 4686.555265951872
  },
  {
    "type": "mouseMovement",
    "timestamp": "2024-08-20T00:47:30.982Z",
    "totalMouseMovement": 4754.297424169631
  },
  {
    "type": "mouseMovement",
    "timestamp": "2024-08-20T00:47:30.999Z",
    "totalMouseMovement": 4882.710819109567
  },
  {
    "type": "mouseMovement",
    "timestamp": "2024-08-20T00:47:31.017Z",
    "totalMouseMovement": 4981.569303823829
  },
  {
    "type": "mouseMovement",
    "timestamp": "2024-08-20T00:47:31.028Z",
    "totalMouseMovement": 5030.661054658363
  },
  {
    "type": "idle",
    "timestamp": "2024-08-20T00:47:33.030Z",
    "duration": 2002
  },
  {
    "type": "mouseMovement",
    "timestamp": "2024-08-20T00:47:36.028Z",
    "totalMouseMovement": 5071.770664240552
  },
  {
    "type": "mouseMovement",
    "timestamp": "2024-08-20T00:47:36.045Z",
    "totalMouseMovement": 5154.921130264502
  },
  {
    "type": "mouseMovement",
    "timestamp": "2024-08-20T00:47:36.061Z",
    "totalMouseMovement": 5232.921130264502
  },
  {
    "type": "mouseMovement",
    "timestamp": "2024-08-20T00:47:36.078Z",
    "totalMouseMovement": 5302.921130264502
  },
  {
    "type": "mouseMovement",
    "timestamp": "2024-08-20T00:47:36.095Z",
    "totalMouseMovement": 5359.921130264502
  },
  {
    "type": "mouseMovement",
    "timestamp": "2024-08-20T00:47:36.111Z",
    "totalMouseMovement": 5401.921130264502
  },
  {
    "type": "mouseMovement",
    "timestamp": "2024-08-20T00:47:36.128Z",
    "totalMouseMovement": 5424.921130264502
  },
  {
    "type": "mouseMovement",
    "timestamp": "2024-08-20T00:47:36.145Z",
    "totalMouseMovement": 5441.921130264502
  },
  {
    "type": "mouseMovement",
    "timestamp": "2024-08-20T00:47:36.161Z",
    "totalMouseMovement": 5451.921130264502
  },
  {
    "type": "mouseMovement",
    "timestamp": "2024-08-20T00:47:36.178Z",
    "totalMouseMovement": 5458.245685584839
  },
  {
    "type": "mouseMovement",
    "timestamp": "2024-08-20T00:47:36.196Z",
    "totalMouseMovement": 5464.328448115137
  },
  {
    "type": "mouseMovement",
    "timestamp": "2024-08-20T00:47:36.211Z",
    "totalMouseMovement": 5472.328448115137
  },
  {
    "type": "mouseMovement",
    "timestamp": "2024-08-20T00:47:36.228Z",
    "totalMouseMovement": 5473.328448115137
  },
  {
    "type": "mouseMovement",
    "timestamp": "2024-08-20T00:47:36.244Z",
    "totalMouseMovement": 5480.3995159270025
  },
  {
    "type": "mouseMovement",
    "timestamp": "2024-08-20T00:47:36.261Z",
    "totalMouseMovement": 5483.3995159270025
  },
  {
    "type": "mouseMovement",
    "timestamp": "2024-08-20T00:47:36.278Z",
    "totalMouseMovement": 5484.3995159270025
  },
  {
    "type": "mouseMovement",
    "timestamp": "2024-08-20T00:47:36.294Z",
    "totalMouseMovement": 5485.813729489376
  },
  {
    "type": "mouseMovement",
    "timestamp": "2024-08-20T00:47:36.295Z",
    "totalMouseMovement": 5488.049797466876
  },
  {
    "type": "mouseMovement",
    "timestamp": "2024-08-20T00:47:36.311Z",
    "totalMouseMovement": 5489.464011029249
  },
  {
    "type": "mouseMovement",
    "timestamp": "2024-08-20T00:47:36.328Z",
    "totalMouseMovement": 5491.70007900675
  },
  {
    "type": "mouseMovement",
    "timestamp": "2024-08-20T00:47:36.345Z",
    "totalMouseMovement": 5495.305630282213
  },
  {
    "type": "mouseMovement",
    "timestamp": "2024-08-20T00:47:36.362Z",
    "totalMouseMovement": 5500.305630282213
  },
  {
    "type": "mouseMovement",
    "timestamp": "2024-08-20T00:47:36.378Z",
    "totalMouseMovement": 5508.907955549256
  },
  {
    "type": "mouseMovement",
    "timestamp": "2024-08-20T00:47:36.395Z",
    "totalMouseMovement": 5518.127500006549
  },
  {
    "type": "mouseMovement",
    "timestamp": "2024-08-20T00:47:36.411Z",
    "totalMouseMovement": 5530.933748481415
  },
  {
    "type": "mouseMovement",
    "timestamp": "2024-08-20T00:47:36.428Z",
    "totalMouseMovement": 5534.096026141583
  },
  {
    "type": "mouseMovement",
    "timestamp": "2024-08-20T00:47:36.446Z",
    "totalMouseMovement": 5543.040298051582
  },
  {
    "type": "mouseMovement",
    "timestamp": "2024-08-20T00:47:36.462Z",
    "totalMouseMovement": 5554.442052302573
  },
  {
    "type": "mouseMovement",
    "timestamp": "2024-08-20T00:47:36.477Z",
    "totalMouseMovement": 5558.914188257572
  },
  {
    "type": "mouseMovement",
    "timestamp": "2024-08-20T00:47:36.494Z",
    "totalMouseMovement": 5561.150256235072
  },
  {
    "type": "mouseMovement",
    "timestamp": "2024-08-20T00:47:36.512Z",
    "totalMouseMovement": 5562.150256235072
  },
  {
    "type": "click",
    "e": "click",
    "timestamp": "2024-08-20T00:47:36.632Z",
    "target": "TEXTAREA",
    "x": 234,
    "y": 393
  },
  {
    "type": "paste",
    "timestamp": "2024-08-20T00:47:36.891Z",
    "text": "2 litres of 180 proof liquor\nFirst-aid kit\nMagnetic compass\nA book entitled ‘Desert Animals That Can Be Eaten’\n2 litres of water per person\nAir map of the area\nFolding knife\nBottle of 1000 salt tablets\nSunglasses (for everyone)\nOvercoat (for everyone)\nTorch with 4 battery-cells\n45 calibre pistol (loaded)\nCosmetic mirror\nPlastic raincoat (large size)\nParachute (red & white)",
    "textLength": 375
  },
  {
    "type": "mouseMovement",
    "timestamp": "2024-08-20T00:47:37.158Z",
    "totalMouseMovement": 5563.150256235072
  },
  {
    "type": "mouseMovement",
    "timestamp": "2024-08-20T00:47:37.189Z",
    "totalMouseMovement": 5566.150256235072
  },
  {
    "type": "mouseMovement",
    "timestamp": "2024-08-20T00:47:37.194Z",
    "totalMouseMovement": 5569.150256235072
  },
  {
    "type": "mouseMovement",
    "timestamp": "2024-08-20T00:47:37.210Z",
    "totalMouseMovement": 5571.386324212573
  },
  {
    "type": "mouseMovement",
    "timestamp": "2024-08-20T00:47:37.227Z",
    "totalMouseMovement": 5579.988649479616
  },
  {
    "type": "mouseMovement",
    "timestamp": "2024-08-20T00:47:37.244Z",
    "totalMouseMovement": 5591.168989367115
  },
  {
    "type": "mouseMovement",
    "timestamp": "2024-08-20T00:47:37.261Z",
    "totalMouseMovement": 5604.510653431241
  },
  {
    "type": "mouseMovement",
    "timestamp": "2024-08-20T00:47:37.278Z",
    "totalMouseMovement": 5615.912407682232
  },
  {
    "type": "mouseMovement",
    "timestamp": "2024-08-20T00:47:37.294Z",
    "totalMouseMovement": 5634.160695273126
  },
  {
    "type": "mouseMovement",
    "timestamp": "2024-08-20T00:47:37.311Z",
    "totalMouseMovement": 5644.160695273126
  },
  {
    "type": "mouseMovement",
    "timestamp": "2024-08-20T00:47:37.328Z",
    "totalMouseMovement": 5654.160695273126
  },
  {
    "type": "mouseMovement",
    "timestamp": "2024-08-20T00:47:37.345Z",
    "totalMouseMovement": 5663.380239730419
  },
  {
    "type": "mouseMovement",
    "timestamp": "2024-08-20T00:47:37.361Z",
    "totalMouseMovement": 5671.626450981655
  },
  {
    "type": "mouseMovement",
    "timestamp": "2024-08-20T00:47:37.378Z",
    "totalMouseMovement": 5680.170454726972
  },
  {
    "type": "mouseMovement",
    "timestamp": "2024-08-20T00:47:37.394Z",
    "totalMouseMovement": 5688.23271247527
  },
  {
    "type": "mouseMovement",
    "timestamp": "2024-08-20T00:47:37.410Z",
    "totalMouseMovement": 5691.061139600016
  },
  {
    "type": "mouseMovement",
    "timestamp": "2024-08-20T00:47:37.427Z",
    "totalMouseMovement": 5694.66669087548
  },
  {
    "type": "mouseMovement",
    "timestamp": "2024-08-20T00:47:37.444Z",
    "totalMouseMovement": 5697.66669087548
  },
  {
    "type": "mouseMovement",
    "timestamp": "2024-08-20T00:47:37.460Z",
    "totalMouseMovement": 5699.90275885298
  },
  {
    "type": "mouseMovement",
    "timestamp": "2024-08-20T00:47:37.476Z",
    "totalMouseMovement": 5704.374894807979
  },
  {
    "type": "mouseMovement",
    "timestamp": "2024-08-20T00:47:37.493Z",
    "totalMouseMovement": 5707.980446083443
  },
  {
    "type": "mouseMovement",
    "timestamp": "2024-08-20T00:47:37.510Z",
    "totalMouseMovement": 5710.808873208189
  },
  {
    "type": "mouseMovement",
    "timestamp": "2024-08-20T00:47:37.528Z",
    "totalMouseMovement": 5712.808873208189
  },
  {
    "type": "mouseMovement",
    "timestamp": "2024-08-20T00:47:37.544Z",
    "totalMouseMovement": 5715.044941185689
  },
  {
    "type": "mouseMovement",
    "timestamp": "2024-08-20T00:47:37.561Z",
    "totalMouseMovement": 5717.044941185689
  },
  {
    "type": "mouseMovement",
    "timestamp": "2024-08-20T00:47:37.578Z",
    "totalMouseMovement": 5721.517077140688
  },
  {
    "type": "mouseMovement",
    "timestamp": "2024-08-20T00:47:37.597Z",
    "totalMouseMovement": 5723.517077140688
  },
  {
    "type": "mouseMovement",
    "timestamp": "2024-08-20T00:47:37.611Z",
    "totalMouseMovement": 5724.517077140688
  },
  {
    "type": "mouseMovement",
    "timestamp": "2024-08-20T00:47:37.627Z",
    "totalMouseMovement": 5725.517077140688
  },
  {
    "type": "mouseMovement",
    "timestamp": "2024-08-20T00:47:37.645Z",
    "totalMouseMovement": 5726.517077140688
  },
  {
    "type": "mouseMovement",
    "timestamp": "2024-08-20T00:47:37.660Z",
    "totalMouseMovement": 5730.517077140688
  },
  {
    "type": "click",
    "e": "click",
    "timestamp": "2024-08-20T00:47:37.845Z",
    "target": "DIV",
    "x": 76,
    "y": 389
  },
  {
    "type": "mouseMovement",
    "timestamp": "2024-08-20T00:47:38.110Z",
    "totalMouseMovement": 5731.931290703062
  },
  {
    "type": "mouseMovement",
    "timestamp": "2024-08-20T00:47:38.227Z",
    "totalMouseMovement": 5732.931290703062
  },
  {
    "type": "mouseMovement",
    "timestamp": "2024-08-20T00:47:38.243Z",
    "totalMouseMovement": 5733.931290703062
  },
  {
    "type": "mouseMovement",
    "timestamp": "2024-08-20T00:47:38.259Z",
    "totalMouseMovement": 5735.931290703062
  },
  {
    "type": "mouseMovement",
    "timestamp": "2024-08-20T00:47:38.772Z",
    "totalMouseMovement": 5737.345504265435
  },
  {
    "type": "mouseMovement",
    "timestamp": "2024-08-20T00:47:38.780Z",
    "totalMouseMovement": 5738.345504265435
  },
  {
    "type": "mouseMovement",
    "timestamp": "2024-08-20T00:47:38.804Z",
    "totalMouseMovement": 5739.759717827808
  },
  {
    "type": "mouseMovement",
    "timestamp": "2024-08-20T00:47:38.812Z",
    "totalMouseMovement": 5740.759717827808
  },
  {
    "type": "click",
    "e": "click",
    "timestamp": "2024-08-20T00:47:38.988Z",
    "target": "TEXTAREA",
    "x": 82,
    "y": 391
  },
  {
    "type": "keypress",
    "timestamp": "2024-08-20T00:47:40.284Z",
    "key": "1",
    "keyCode": 49,
    "target": "TEXTAREA"
  },
  {
    "type": "keypress",
    "timestamp": "2024-08-20T00:47:40.565Z",
    "key": ".",
    "keyCode": 46,
    "target": "TEXTAREA"
  },
  {
    "type": "keypress",
    "timestamp": "2024-08-20T00:47:41.179Z",
    "key": " ",
    "keyCode": 32,
    "target": "TEXTAREA"
  },
  {
    "type": "keypress",
    "timestamp": "2024-08-20T00:47:42.671Z",
    "key": "2",
    "keyCode": 50,
    "target": "TEXTAREA"
  },
  {
    "type": "keypress",
    "timestamp": "2024-08-20T00:47:43.161Z",
    "key": "/",
    "keyCode": 47,
    "target": "TEXTAREA"
  },
  {
    "type": "deleteAction",
    "timestamp": "2024-08-20T00:47:43.633Z",
    "key": "Backspace"
  },
  {
    "type": "keypress",
    "timestamp": "2024-08-20T00:47:43.876Z",
    "key": ".",
    "keyCode": 46,
    "target": "TEXTAREA"
  },
  {
    "type": "keypress",
    "timestamp": "2024-08-20T00:47:44.049Z",
    "key": " ",
    "keyCode": 32,
    "target": "TEXTAREA"
  },
  {
    "type": "idle",
    "timestamp": "2024-08-20T00:47:46.055Z",
    "duration": 2006
  },
  {
    "type": "keypress",
    "timestamp": "2024-08-20T00:47:47.922Z",
    "key": "3",
    "keyCode": 51,
    "target": "TEXTAREA"
  },
  {
    "type": "keypress",
    "timestamp": "2024-08-20T00:47:49.080Z",
    "key": ".",
    "keyCode": 46,
    "target": "TEXTAREA"
  },
  {
    "type": "keypress",
    "timestamp": "2024-08-20T00:47:49.237Z",
    "key": " ",
    "keyCode": 32,
    "target": "TEXTAREA"
  },
  {
    "type": "keypress",
    "timestamp": "2024-08-20T00:47:50.378Z",
    "key": "4",
    "keyCode": 52,
    "target": "TEXTAREA"
  },
  {
    "type": "keypress",
    "timestamp": "2024-08-20T00:47:50.642Z",
    "key": "/",
    "keyCode": 47,
    "target": "TEXTAREA"
  },
  {
    "type": "keypress",
    "timestamp": "2024-08-20T00:47:50.938Z",
    "key": " ",
    "keyCode": 32,
    "target": "TEXTAREA"
  },
  {
    "type": "deleteAction",
    "timestamp": "2024-08-20T00:47:51.344Z",
    "key": "Backspace"
  },
  {
    "type": "deleteAction",
    "timestamp": "2024-08-20T00:47:51.496Z",
    "key": "Backspace"
  },
  {
    "type": "keypress",
    "timestamp": "2024-08-20T00:47:51.748Z",
    "key": "/",
    "keyCode": 47,
    "target": "TEXTAREA"
  },
  {
    "type": "deleteAction",
    "timestamp": "2024-08-20T00:47:52.291Z",
    "key": "Backspace"
  },
  {
    "type": "keypress",
    "timestamp": "2024-08-20T00:47:52.879Z",
    "key": ".",
    "keyCode": 46,
    "target": "TEXTAREA"
  },
  {
    "type": "keypress",
    "timestamp": "2024-08-20T00:47:53.108Z",
    "key": " ",
    "keyCode": 32,
    "target": "TEXTAREA"
  },
  {
    "type": "keypress",
    "timestamp": "2024-08-20T00:47:54.383Z",
    "key": "5",
    "keyCode": 53,
    "target": "TEXTAREA"
  },
  {
    "type": "keypress",
    "timestamp": "2024-08-20T00:47:54.736Z",
    "key": "/",
    "keyCode": 47,
    "target": "TEXTAREA"
  },
  {
    "type": "deleteAction",
    "timestamp": "2024-08-20T00:47:55.319Z",
    "key": "Backspace"
  },
  {
    "type": "keypress",
    "timestamp": "2024-08-20T00:47:55.896Z",
    "key": ".",
    "keyCode": 46,
    "target": "TEXTAREA"
  },
  {
    "type": "keypress",
    "timestamp": "2024-08-20T00:47:56.126Z",
    "key": " ",
    "keyCode": 32,
    "target": "TEXTAREA"
  },
  {
    "type": "keypress",
    "timestamp": "2024-08-20T00:47:57.987Z",
    "key": "6",
    "keyCode": 54,
    "target": "TEXTAREA"
  },
  {
    "type": "keypress",
    "timestamp": "2024-08-20T00:47:58.459Z",
    "key": ".",
    "keyCode": 46,
    "target": "TEXTAREA"
  },
  {
    "type": "keypress",
    "timestamp": "2024-08-20T00:47:58.914Z",
    "key": " ",
    "keyCode": 32,
    "target": "TEXTAREA"
  },
  {
    "type": "keypress",
    "timestamp": "2024-08-20T00:48:00.726Z",
    "key": "7",
    "keyCode": 55,
    "target": "TEXTAREA"
  },
  {
    "type": "keypress",
    "timestamp": "2024-08-20T00:48:01.659Z",
    "key": ".",
    "keyCode": 46,
    "target": "TEXTAREA"
  },
  {
    "type": "keypress",
    "timestamp": "2024-08-20T00:48:02.307Z",
    "key": " ",
    "keyCode": 32,
    "target": "TEXTAREA"
  },
  {
    "type": "keypress",
    "timestamp": "2024-08-20T00:48:04.222Z",
    "key": "8",
    "keyCode": 56,
    "target": "TEXTAREA"
  },
  {
    "type": "keypress",
    "timestamp": "2024-08-20T00:48:05.055Z",
    "key": ".",
    "keyCode": 46,
    "target": "TEXTAREA"
  },
  {
    "type": "keypress",
    "timestamp": "2024-08-20T00:48:05.313Z",
    "key": " ",
    "keyCode": 32,
    "target": "TEXTAREA"
  },
  {
    "type": "keypress",
    "timestamp": "2024-08-20T00:48:06.937Z",
    "key": "9",
    "keyCode": 57,
    "target": "TEXTAREA"
  },
  {
    "type": "keypress",
    "timestamp": "2024-08-20T00:48:07.769Z",
    "key": ".",
    "keyCode": 46,
    "target": "TEXTAREA"
  },
  {
    "type": "keypress",
    "timestamp": "2024-08-20T00:48:07.953Z",
    "key": " ",
    "keyCode": 32,
    "target": "TEXTAREA"
  },
  {
    "type": "keypress",
    "timestamp": "2024-08-20T00:48:09.275Z",
    "key": "1",
    "keyCode": 49,
    "target": "TEXTAREA"
  },
  {
    "type": "keypress",
    "timestamp": "2024-08-20T00:48:09.637Z",
    "key": "9",
    "keyCode": 57,
    "target": "TEXTAREA"
  },
  {
    "type": "deleteAction",
    "timestamp": "2024-08-20T00:48:10.069Z",
    "key": "Backspace"
  },
  {
    "type": "keypress",
    "timestamp": "2024-08-20T00:48:10.300Z",
    "key": "0",
    "keyCode": 48,
    "target": "TEXTAREA"
  },
  {
    "type": "keypress",
    "timestamp": "2024-08-20T00:48:10.915Z",
    "key": ".",
    "keyCode": 46,
    "target": "TEXTAREA"
  },
  {
    "type": "keypress",
    "timestamp": "2024-08-20T00:48:11.118Z",
    "key": " ",
    "keyCode": 32,
    "target": "TEXTAREA"
  },
  {
    "type": "keypress",
    "timestamp": "2024-08-20T00:48:12.194Z",
    "key": "1",
    "keyCode": 49,
    "target": "TEXTAREA"
  },
  {
    "type": "keypress",
    "timestamp": "2024-08-20T00:48:12.389Z",
    "key": "1",
    "keyCode": 49,
    "target": "TEXTAREA"
  },
  {
    "type": "keypress",
    "timestamp": "2024-08-20T00:48:13.414Z",
    "key": ".",
    "keyCode": 46,
    "target": "TEXTAREA"
  },
  {
    "type": "keypress",
    "timestamp": "2024-08-20T00:48:13.604Z",
    "key": " ",
    "keyCode": 32,
    "target": "TEXTAREA"
  },
  {
    "type": "keypress",
    "timestamp": "2024-08-20T00:48:14.792Z",
    "key": "1",
    "keyCode": 49,
    "target": "TEXTAREA"
  },
  {
    "type": "keypress",
    "timestamp": "2024-08-20T00:48:14.989Z",
    "key": "2",
    "keyCode": 50,
    "target": "TEXTAREA"
  },
  {
    "type": "keypress",
    "timestamp": "2024-08-20T00:48:15.994Z",
    "key": ".",
    "keyCode": 46,
    "target": "TEXTAREA"
  },
  {
    "type": "keypress",
    "timestamp": "2024-08-20T00:48:16.194Z",
    "key": " ",
    "keyCode": 32,
    "target": "TEXTAREA"
  },
  {
    "type": "keypress",
    "timestamp": "2024-08-20T00:48:17.296Z",
    "key": "1",
    "keyCode": 49,
    "target": "TEXTAREA"
  },
  {
    "type": "keypress",
    "timestamp": "2024-08-20T00:48:17.414Z",
    "key": "3",
    "keyCode": 51,
    "target": "TEXTAREA"
  },
  {
    "type": "keypress",
    "timestamp": "2024-08-20T00:48:18.438Z",
    "key": ".",
    "keyCode": 46,
    "target": "TEXTAREA"
  },
  {
    "type": "keypress",
    "timestamp": "2024-08-20T00:48:18.828Z",
    "key": " ",
    "keyCode": 32,
    "target": "TEXTAREA"
  },
  {
    "type": "keypress",
    "timestamp": "2024-08-20T00:48:20.152Z",
    "key": "1",
    "keyCode": 49,
    "target": "TEXTAREA"
  },
  {
    "type": "keypress",
    "timestamp": "2024-08-20T00:48:20.271Z",
    "key": "4",
    "keyCode": 52,
    "target": "TEXTAREA"
  },
  {
    "type": "keypress",
    "timestamp": "2024-08-20T00:48:20.684Z",
    "key": "/",
    "keyCode": 47,
    "target": "TEXTAREA"
  },
  {
    "type": "deleteAction",
    "timestamp": "2024-08-20T00:48:21.271Z",
    "key": "Backspace"
  },
  {
    "type": "keypress",
    "timestamp": "2024-08-20T00:48:21.534Z",
    "key": ".",
    "keyCode": 46,
    "target": "TEXTAREA"
  },
  {
    "type": "keypress",
    "timestamp": "2024-08-20T00:48:22.101Z",
    "key": " ",
    "keyCode": 32,
    "target": "TEXTAREA"
  },
  {
    "type": "keypress",
    "timestamp": "2024-08-20T00:48:23.289Z",
    "key": "1",
    "keyCode": 49,
    "target": "TEXTAREA"
  },
  {
    "type": "keypress",
    "timestamp": "2024-08-20T00:48:23.422Z",
    "key": "5",
    "keyCode": 53,
    "target": "TEXTAREA"
  },
  {
    "type": "keypress",
    "timestamp": "2024-08-20T00:48:24.444Z",
    "key": ".",
    "keyCode": 46,
    "target": "TEXTAREA"
  },
  {
    "type": "keypress",
    "timestamp": "2024-08-20T00:48:24.610Z",
    "key": " ",
    "keyCode": 32,
    "target": "TEXTAREA"
  },
  {
    "type": "mouseMovement",
    "timestamp": "2024-08-20T00:48:25.283Z",
    "totalMouseMovement": 5742.759717827808
  },
  {
    "type": "mouseMovement",
    "timestamp": "2024-08-20T00:48:25.293Z",
    "totalMouseMovement": 5747.858737341401
  },
  {
    "type": "mouseMovement",
    "timestamp": "2024-08-20T00:48:25.301Z",
    "totalMouseMovement": 5760.228054218254
  },
  {
    "type": "mouseMovement",
    "timestamp": "2024-08-20T00:48:25.319Z",
    "totalMouseMovement": 5784.579645542026
  },
  {
    "type": "mouseMovement",
    "timestamp": "2024-08-20T00:48:25.335Z",
    "totalMouseMovement": 5810.656455162836
  },
  {
    "type": "mouseMovement",
    "timestamp": "2024-08-20T00:48:25.352Z",
    "totalMouseMovement": 5837.283509074225
  },
  {
    "type": "mouseMovement",
    "timestamp": "2024-08-20T00:48:25.368Z",
    "totalMouseMovement": 5881.112723075847
  },
  {
    "type": "mouseMovement",
    "timestamp": "2024-08-20T00:48:25.385Z",
    "totalMouseMovement": 5930.306218580842
  },
  {
    "type": "mouseMovement",
    "timestamp": "2024-08-20T00:48:25.402Z",
    "totalMouseMovement": 5977.433705252635
  },
  {
    "type": "mouseMovement",
    "timestamp": "2024-08-20T00:48:25.419Z",
    "totalMouseMovement": 6019.493186942262
  },
  {
    "type": "mouseMovement",
    "timestamp": "2024-08-20T00:48:25.435Z",
    "totalMouseMovement": 6074.95488543771
  },
  {
    "type": "mouseMovement",
    "timestamp": "2024-08-20T00:48:25.452Z",
    "totalMouseMovement": 6105.187318353372
  },
  {
    "type": "mouseMovement",
    "timestamp": "2024-08-20T00:48:25.469Z",
    "totalMouseMovement": 6125.995970400057
  },
  {
    "type": "mouseMovement",
    "timestamp": "2024-08-20T00:48:25.485Z",
    "totalMouseMovement": 6137.397724651048
  },
  {
    "type": "mouseMovement",
    "timestamp": "2024-08-20T00:48:25.501Z",
    "totalMouseMovement": 6141.869860606047
  },
  {
    "type": "mouseMovement",
    "timestamp": "2024-08-20T00:48:25.644Z",
    "totalMouseMovement": 6142.869860606047
  },
  {
    "type": "mouseMovement",
    "timestamp": "2024-08-20T00:48:25.685Z",
    "totalMouseMovement": 6147.96888011964
  },
  {
    "type": "mouseMovement",
    "timestamp": "2024-08-20T00:48:25.702Z",
    "totalMouseMovement": 6164.96888011964
  },
  {
    "type": "mouseMovement",
    "timestamp": "2024-08-20T00:48:25.718Z",
    "totalMouseMovement": 6181.093395616237
  },
  {
    "type": "mouseMovement",
    "timestamp": "2024-08-20T00:48:25.734Z",
    "totalMouseMovement": 6197.585818118708
  },
  {
    "type": "mouseMovement",
    "timestamp": "2024-08-20T00:48:25.753Z",
    "totalMouseMovement": 6213.109992814968
  },
  {
    "type": "mouseMovement",
    "timestamp": "2024-08-20T00:48:25.769Z",
    "totalMouseMovement": 6226.711463323703
  },
  {
    "type": "mouseMovement",
    "timestamp": "2024-08-20T00:48:25.785Z",
    "totalMouseMovement": 6234.327236429567
  },
  {
    "type": "mouseMovement",
    "timestamp": "2024-08-20T00:48:25.802Z",
    "totalMouseMovement": 6258.1809573133205
  },
  {
    "type": "mouseMovement",
    "timestamp": "2024-08-20T00:48:25.818Z",
    "totalMouseMovement": 6270.987205788186
  },
  {
    "type": "mouseMovement",
    "timestamp": "2024-08-20T00:48:25.835Z",
    "totalMouseMovement": 6282.300914287171
  },
  {
    "type": "mouseMovement",
    "timestamp": "2024-08-20T00:48:25.851Z",
    "totalMouseMovement": 6291.520458744463
  },
  {
    "type": "mouseMovement",
    "timestamp": "2024-08-20T00:48:25.868Z",
    "totalMouseMovement": 6295.992594699463
  },
  {
    "type": "mouseMovement",
    "timestamp": "2024-08-20T00:48:25.885Z",
    "totalMouseMovement": 6303.063662511328
  },
  {
    "type": "mouseMovement",
    "timestamp": "2024-08-20T00:48:25.902Z",
    "totalMouseMovement": 6307.3063031984475
  },
  {
    "type": "mousewheel",
    "timestamp": "2024-08-20T00:48:25.902Z",
    "deltaY": 100
  },
  {
    "type": "mouseMovement",
    "timestamp": "2024-08-20T00:48:25.917Z",
    "totalMouseMovement": 6312.3063031984475
  },
  {
    "type": "mouseMovement",
    "timestamp": "2024-08-20T00:48:25.935Z",
    "totalMouseMovement": 6317.691468005582
  },
  {
    "type": "mouseMovement",
    "timestamp": "2024-08-20T00:48:25.951Z",
    "totalMouseMovement": 6319.927535983082
  },
  {
    "type": "mousewheel",
    "timestamp": "2024-08-20T00:48:25.952Z",
    "deltaY": 100
  },
  {
    "type": "mouseMovement",
    "timestamp": "2024-08-20T00:48:25.968Z",
    "totalMouseMovement": 6322.163603960582
  },
  {
    "type": "mouseMovement",
    "timestamp": "2024-08-20T00:48:25.984Z",
    "totalMouseMovement": 6324.399671938082
  },
  {
    "type": "mousewheel",
    "timestamp": "2024-08-20T00:48:25.985Z",
    "deltaY": 100
  },
  {
    "type": "mousewheel",
    "timestamp": "2024-08-20T00:48:26.251Z",
    "deltaY": 100
  },
  {
    "type": "mousewheel",
    "timestamp": "2024-08-20T00:48:26.267Z",
    "deltaY": 100
  },
  {
    "type": "mousewheel",
    "timestamp": "2024-08-20T00:48:26.301Z",
    "deltaY": 100
  },
  {
    "type": "scroll",
    "timestamp": "2024-08-20T00:48:26.806Z",
    "deltaY": 100
  },
  {
    "type": "mousewheel",
    "timestamp": "2024-08-20T00:48:26.817Z",
    "deltaY": 100
  },
  {
    "type": "mousewheel",
    "timestamp": "2024-08-20T00:48:26.866Z",
    "deltaY": 100
  },
  {
    "type": "mousewheel",
    "timestamp": "2024-08-20T00:48:26.900Z",
    "deltaY": 100
  },
  {
    "type": "scroll",
    "timestamp": "2024-08-20T00:48:27.414Z",
    "deltaY": 100
  },
  {
    "type": "mouseMovement",
    "timestamp": "2024-08-20T00:48:27.501Z",
    "totalMouseMovement": 6325.399671938082
  },
  {
    "type": "mouseMovement",
    "timestamp": "2024-08-20T00:48:27.516Z",
    "totalMouseMovement": 6327.635739915582
  },
  {
    "type": "mouseMovement",
    "timestamp": "2024-08-20T00:48:27.534Z",
    "totalMouseMovement": 6339.037494166573
  },
  {
    "type": "mouseMovement",
    "timestamp": "2024-08-20T00:48:27.550Z",
    "totalMouseMovement": 6352.491118213647
  },
  {
    "type": "mouseMovement",
    "timestamp": "2024-08-20T00:48:27.566Z",
    "totalMouseMovement": 6376.197657395906
  },
  {
    "type": "mouseMovement",
    "timestamp": "2024-08-20T00:48:27.583Z",
    "totalMouseMovement": 6417.537710613095
  },
  {
    "type": "mouseMovement",
    "timestamp": "2024-08-20T00:48:27.600Z",
    "totalMouseMovement": 6470.234959118117
  },
  {
    "type": "mouseMovement",
    "timestamp": "2024-08-20T00:48:27.616Z",
    "totalMouseMovement": 6521.635348221703
  },
  {
    "type": "mouseMovement",
    "timestamp": "2024-08-20T00:48:27.635Z",
    "totalMouseMovement": 6578.362766636434
  },
  {
    "type": "mouseMovement",
    "timestamp": "2024-08-20T00:48:27.664Z",
    "totalMouseMovement": 6598.212199877713
  },
  {
    "type": "mouseMovement",
    "timestamp": "2024-08-20T00:48:27.679Z",
    "totalMouseMovement": 6632.182775380639
  },
  {
    "type": "mouseMovement",
    "timestamp": "2024-08-20T00:48:27.694Z",
    "totalMouseMovement": 6638.585899618072
  },
  {
    "type": "mouseMovement",
    "timestamp": "2024-08-20T00:48:27.699Z",
    "totalMouseMovement": 6648.019880750129
  },
  {
    "type": "mouseMovement",
    "timestamp": "2024-08-20T00:48:27.817Z",
    "totalMouseMovement": 6657.019880750129
  },
  {
    "type": "mouseMovement",
    "timestamp": "2024-08-20T00:48:27.833Z",
    "totalMouseMovement": 6662.405045557263
  },
  {
    "type": "mouseMovement",
    "timestamp": "2024-08-20T00:48:27.850Z",
    "totalMouseMovement": 6664.405045557263
  },
  {
    "type": "mouseMovement",
    "timestamp": "2024-08-20T00:48:27.917Z",
    "totalMouseMovement": 6668.877181512263
  },
  {
    "type": "mouseMovement",
    "timestamp": "2024-08-20T00:48:27.932Z",
    "totalMouseMovement": 6674.534035761755
  },
  {
    "type": "mouseMovement",
    "timestamp": "2024-08-20T00:48:27.950Z",
    "totalMouseMovement": 6678.657141387373
  },
  {
    "type": "mouseMovement",
    "timestamp": "2024-08-20T00:48:27.967Z",
    "totalMouseMovement": 6681.819419047541
  },
  {
    "type": "mouseMovement",
    "timestamp": "2024-08-20T00:48:27.983Z",
    "totalMouseMovement": 6685.942524673158
  },
  {
    "type": "mouseMovement",
    "timestamp": "2024-08-20T00:48:28.001Z",
    "totalMouseMovement": 6690.065630298775
  },
  {
    "type": "mouseMovement",
    "timestamp": "2024-08-20T00:48:28.017Z",
    "totalMouseMovement": 6694.188735924393
  },
  {
    "type": "mouseMovement",
    "timestamp": "2024-08-20T00:48:28.032Z",
    "totalMouseMovement": 6699.188735924393
  },
  {
    "type": "mouseMovement",
    "timestamp": "2024-08-20T00:48:28.050Z",
    "totalMouseMovement": 6703.188735924393
  },
  {
    "type": "mouseMovement",
    "timestamp": "2024-08-20T00:48:28.067Z",
    "totalMouseMovement": 6708.188735924393
  },
  {
    "type": "mouseMovement",
    "timestamp": "2024-08-20T00:48:28.083Z",
    "totalMouseMovement": 6714.188735924393
  },
  {
    "type": "mouseMovement",
    "timestamp": "2024-08-20T00:48:28.099Z",
    "totalMouseMovement": 6719.287755437986
  },
  {
    "type": "mouseMovement",
    "timestamp": "2024-08-20T00:48:28.117Z",
    "totalMouseMovement": 6724.386774951578
  },
  {
    "type": "mouseMovement",
    "timestamp": "2024-08-20T00:48:28.133Z",
    "totalMouseMovement": 6729.485794465171
  },
  {
    "type": "mouseMovement",
    "timestamp": "2024-08-20T00:48:28.150Z",
    "totalMouseMovement": 6731.721862442671
  },
  {
    "type": "mouseMovement",
    "timestamp": "2024-08-20T00:48:28.166Z",
    "totalMouseMovement": 6734.884140102839
  },
  {
    "type": "mouseMovement",
    "timestamp": "2024-08-20T00:48:28.183Z",
    "totalMouseMovement": 6736.298353665213
  },
  {
    "type": "mouseMovement",
    "timestamp": "2024-08-20T00:48:28.199Z",
    "totalMouseMovement": 6739.9039049406765
  },
  {
    "type": "mouseMovement",
    "timestamp": "2024-08-20T00:48:28.216Z",
    "totalMouseMovement": 6742.139972918177
  },
  {
    "type": "click",
    "e": "click",
    "timestamp": "2024-08-20T00:48:28.344Z",
    "target": "DIV",
    "x": 0,
    "y": 0
  },
  {
    "type": "click",
    "e": "click",
    "timestamp": "2024-08-20T00:48:28.348Z",
    "target": "SPAN",
    "x": 172,
    "y": 506
  },
  {
    "type": "mouseMovement",
    "timestamp": "2024-08-20T00:48:28.533Z",
    "totalMouseMovement": 6743.139972918177
  },
  {
    "type": "mouseMovement",
    "timestamp": "2024-08-20T00:48:28.599Z",
    "totalMouseMovement": 6744.139972918177
  },
  {
    "type": "mouseMovement",
    "timestamp": "2024-08-20T00:48:28.616Z",
    "totalMouseMovement": 6745.139972918177
  },
  {
    "type": "mouseMovement",
    "timestamp": "2024-08-20T00:48:28.634Z",
    "totalMouseMovement": 6747.139972918177
  },
  {
    "type": "mouseMovement",
    "timestamp": "2024-08-20T00:48:28.651Z",
    "totalMouseMovement": 6750.74552419364
  },
  {
    "type": "mouseMovement",
    "timestamp": "2024-08-20T00:48:28.668Z",
    "totalMouseMovement": 6756.1306890007745
  },
  {
    "type": "mouseMovement",
    "timestamp": "2024-08-20T00:48:28.683Z",
    "totalMouseMovement": 6762.455244321111
  },
  {
    "type": "mouseMovement",
    "timestamp": "2024-08-20T00:48:28.700Z",
    "totalMouseMovement": 6769.526312132977
  },
  {
    "type": "mouseMovement",
    "timestamp": "2024-08-20T00:48:28.716Z",
    "totalMouseMovement": 6779.724351160163
  },
  {
    "type": "mouseMovement",
    "timestamp": "2024-08-20T00:48:28.733Z",
    "totalMouseMovement": 6787.786608908461
  },
  {
    "type": "mouseMovement",
    "timestamp": "2024-08-20T00:48:28.749Z",
    "totalMouseMovement": 6799.188363159452
  },
  {
    "type": "mouseMovement",
    "timestamp": "2024-08-20T00:48:28.766Z",
    "totalMouseMovement": 6804.188363159452
  },
  {
    "type": "mouseMovement",
    "timestamp": "2024-08-20T00:48:28.782Z",
    "totalMouseMovement": 6807.793914434916
  },
  {
    "type": "mouseMovement",
    "timestamp": "2024-08-20T00:48:28.800Z",
    "totalMouseMovement": 6810.622341559661
  },
  {
    "type": "mouseMovement",
    "timestamp": "2024-08-20T00:48:28.815Z",
    "totalMouseMovement": 6815.094477514661
  },
  {
    "type": "mousewheel",
    "timestamp": "2024-08-20T00:48:28.839Z",
    "deltaY": -100
  },
  {
    "type": "mouseMovement",
    "timestamp": "2024-08-20T00:48:28.850Z",
    "totalMouseMovement": 6816.508691077034
  },
  {
    "type": "mousewheel",
    "timestamp": "2024-08-20T00:48:28.866Z",
    "deltaY": -100
  },
  {
    "type": "mousewheel",
    "timestamp": "2024-08-20T00:48:28.883Z",
    "deltaY": -100
  },
  {
    "type": "mousewheel",
    "timestamp": "2024-08-20T00:48:28.899Z",
    "deltaY": -100
  },
  {
    "type": "mouseMovement",
    "timestamp": "2024-08-20T00:48:28.932Z",
    "totalMouseMovement": 6818.744759054534
  },
  {
    "type": "mousewheel",
    "timestamp": "2024-08-20T00:48:29.133Z",
    "deltaY": -100
  },
  {
    "type": "mousewheel",
    "timestamp": "2024-08-20T00:48:29.166Z",
    "deltaY": -100
  },
  {
    "type": "mousewheel",
    "timestamp": "2024-08-20T00:48:29.199Z",
    "deltaY": -100
  },
  {
    "type": "mouseMovement",
    "timestamp": "2024-08-20T00:48:29.233Z",
    "totalMouseMovement": 6819.744759054534
  },
  {
    "type": "mouseMovement",
    "timestamp": "2024-08-20T00:48:29.267Z",
    "totalMouseMovement": 6820.744759054534
  },
  {
    "type": "mouseMovement",
    "timestamp": "2024-08-20T00:48:29.283Z",
    "totalMouseMovement": 6822.158972616908
  },
  {
    "type": "mouseMovement",
    "timestamp": "2024-08-20T00:48:29.299Z",
    "totalMouseMovement": 6823.158972616908
  },
  {
    "type": "mouseMovement",
    "timestamp": "2024-08-20T00:48:29.349Z",
    "totalMouseMovement": 6824.158972616908
  },
  {
    "type": "mousewheel",
    "timestamp": "2024-08-20T00:48:29.421Z",
    "deltaY": -100
  },
  {
    "type": "mousewheel",
    "timestamp": "2024-08-20T00:48:29.449Z",
    "deltaY": -100
  },
  {
    "type": "mousewheel",
    "timestamp": "2024-08-20T00:48:29.482Z",
    "deltaY": -100
  },
  {
    "type": "mouseMovement",
    "timestamp": "2024-08-20T00:48:29.617Z",
    "totalMouseMovement": 6825.158972616908
  },
  {
    "type": "mouseMovement",
    "timestamp": "2024-08-20T00:48:29.650Z",
    "totalMouseMovement": 6826.158972616908
  },
  {
    "type": "mouseMovement",
    "timestamp": "2024-08-20T00:48:29.665Z",
    "totalMouseMovement": 6827.158972616908
  },
  {
    "type": "mouseMovement",
    "timestamp": "2024-08-20T00:48:29.681Z",
    "totalMouseMovement": 6846.575460455855
  },
  {
    "type": "mouseMovement",
    "timestamp": "2024-08-20T00:48:29.698Z",
    "totalMouseMovement": 6856.871090596842
  },
  {
    "type": "mouseMovement",
    "timestamp": "2024-08-20T00:48:29.715Z",
    "totalMouseMovement": 6876.287578435789
  },
  {
    "type": "mouseMovement",
    "timestamp": "2024-08-20T00:48:29.731Z",
    "totalMouseMovement": 6889.3259832461945
  },
  {
    "type": "mouseMovement",
    "timestamp": "2024-08-20T00:48:29.748Z",
    "totalMouseMovement": 6900.987887035885
  },
  {
    "type": "mouseMovement",
    "timestamp": "2024-08-20T00:48:29.764Z",
    "totalMouseMovement": 6912.692586946605
  },
  {
    "type": "mouseMovement",
    "timestamp": "2024-08-20T00:48:29.781Z",
    "totalMouseMovement": 6923.132893455516
  },
  {
    "type": "mouseMovement",
    "timestamp": "2024-08-20T00:48:29.798Z",
    "totalMouseMovement": 6934.313233343015
  },
  {
    "type": "mouseMovement",
    "timestamp": "2024-08-20T00:48:29.814Z",
    "totalMouseMovement": 6947.91470385175
  },
  {
    "type": "mouseMovement",
    "timestamp": "2024-08-20T00:48:29.831Z",
    "totalMouseMovement": 6962.679526911984
  },
  {
    "type": "mouseMovement",
    "timestamp": "2024-08-20T00:48:29.848Z",
    "totalMouseMovement": 6977.444349972217
  },
  {
    "type": "mouseMovement",
    "timestamp": "2024-08-20T00:48:29.864Z",
    "totalMouseMovement": 6989.6509055879515
  },
  {
    "type": "mouseMovement",
    "timestamp": "2024-08-20T00:48:29.881Z",
    "totalMouseMovement": 6999.946535728938
  },
  {
    "type": "mouseMovement",
    "timestamp": "2024-08-20T00:48:29.897Z",
    "totalMouseMovement": 7009.380516860995
  },
  {
    "type": "mouseMovement",
    "timestamp": "2024-08-20T00:48:29.914Z",
    "totalMouseMovement": 7019.380516860995
  },
  {
    "type": "mouseMovement",
    "timestamp": "2024-08-20T00:48:29.931Z",
    "totalMouseMovement": 7033.272960850445
  },
  {
    "type": "mouseMovement",
    "timestamp": "2024-08-20T00:48:29.948Z",
    "totalMouseMovement": 7045.314555429238
  },
  {
    "type": "mouseMovement",
    "timestamp": "2024-08-20T00:48:29.964Z",
    "totalMouseMovement": 7057.521111044972
  },
  {
    "type": "mouseMovement",
    "timestamp": "2024-08-20T00:48:29.981Z",
    "totalMouseMovement": 7072.521111044972
  },
  {
    "type": "scroll",
    "timestamp": "2024-08-20T00:48:29.983Z",
    "deltaY": -100
  },
  {
    "type": "mouseMovement",
    "timestamp": "2024-08-20T00:48:29.998Z",
    "totalMouseMovement": 7095.542839911414
  },
  {
    "type": "mouseMovement",
    "timestamp": "2024-08-20T00:48:30.014Z",
    "totalMouseMovement": 7123.560691363658
  },
  {
    "type": "mouseMovement",
    "timestamp": "2024-08-20T00:48:30.031Z",
    "totalMouseMovement": 7154.9613282998735
  },
  {
    "type": "mouseMovement",
    "timestamp": "2024-08-20T00:48:30.048Z",
    "totalMouseMovement": 7192.6972528281
  },
  {
    "type": "mouseMovement",
    "timestamp": "2024-08-20T00:48:30.064Z",
    "totalMouseMovement": 7236.6062496283
  },
  {
    "type": "mouseMovement",
    "timestamp": "2024-08-20T00:48:30.081Z",
    "totalMouseMovement": 7281.024714257326
  },
  {
    "type": "mouseMovement",
    "timestamp": "2024-08-20T00:48:30.098Z",
    "totalMouseMovement": 7323.568809029692
  },
  {
    "type": "mouseMovement",
    "timestamp": "2024-08-20T00:48:30.114Z",
    "totalMouseMovement": 7358.554520398763
  },
  {
    "type": "mouseMovement",
    "timestamp": "2024-08-20T00:48:30.131Z",
    "totalMouseMovement": 7386.013580834255
  },
  {
    "type": "mouseMovement",
    "timestamp": "2024-08-20T00:48:30.147Z",
    "totalMouseMovement": 7391.013580834255
  },
  {
    "type": "mouseMovement",
    "timestamp": "2024-08-20T00:48:30.164Z",
    "totalMouseMovement": 7392.013580834255
  },
  {
    "type": "mouseMovement",
    "timestamp": "2024-08-20T00:48:30.187Z",
    "totalMouseMovement": 7393.013580834255
  },
  {
    "type": "mouseMovement",
    "timestamp": "2024-08-20T00:48:30.248Z",
    "totalMouseMovement": 7396.175858494423
  },
  {
    "type": "mouseMovement",
    "timestamp": "2024-08-20T00:48:30.265Z",
    "totalMouseMovement": 7397.175858494423
  },
  {
    "type": "mouseMovement",
    "timestamp": "2024-08-20T00:48:30.281Z",
    "totalMouseMovement": 7398.175858494423
  },
  {
    "type": "mouseMovement",
    "timestamp": "2024-08-20T00:48:30.298Z",
    "totalMouseMovement": 7400.411926471923
  },
  {
    "type": "mouseMovement",
    "timestamp": "2024-08-20T00:48:30.316Z",
    "totalMouseMovement": 7402.647994449423
  },
  {
    "type": "mouseMovement",
    "timestamp": "2024-08-20T00:48:30.331Z",
    "totalMouseMovement": 7405.810272109591
  },
  {
    "type": "mouseMovement",
    "timestamp": "2024-08-20T00:48:30.347Z",
    "totalMouseMovement": 7410.810272109591
  },
  {
    "type": "mouseMovement",
    "timestamp": "2024-08-20T00:48:30.364Z",
    "totalMouseMovement": 7415.810272109591
  },
  {
    "type": "mouseMovement",
    "timestamp": "2024-08-20T00:48:30.382Z",
    "totalMouseMovement": 7422.518476042091
  },
  {
    "type": "mouseMovement",
    "timestamp": "2024-08-20T00:48:30.397Z",
    "totalMouseMovement": 7431.952457174148
  },
  {
    "type": "mouseMovement",
    "timestamp": "2024-08-20T00:48:30.414Z",
    "totalMouseMovement": 7441.386438306205
  },
  {
    "type": "mouseMovement",
    "timestamp": "2024-08-20T00:48:30.431Z",
    "totalMouseMovement": 7449.448696054503
  },
  {
    "type": "mouseMovement",
    "timestamp": "2024-08-20T00:48:30.447Z",
    "totalMouseMovement": 7454.448696054503
  },
  {
    "type": "mouseMovement",
    "timestamp": "2024-08-20T00:48:30.464Z",
    "totalMouseMovement": 7457.610973714671
  },
  {
    "type": "mouseMovement",
    "timestamp": "2024-08-20T00:48:30.858Z",
    "totalMouseMovement": 7459.025187277044
  },
  {
    "type": "mouseMovement",
    "timestamp": "2024-08-20T00:48:30.866Z",
    "totalMouseMovement": 7460.025187277044
  },
  {
    "type": "mouseMovement",
    "timestamp": "2024-08-20T00:48:30.880Z",
    "totalMouseMovement": 7462.025187277044
  },
  {
    "type": "mouseMovement",
    "timestamp": "2024-08-20T00:48:30.897Z",
    "totalMouseMovement": 7465.630738552508
  },
  {
    "type": "mouseMovement",
    "timestamp": "2024-08-20T00:48:30.913Z",
    "totalMouseMovement": 7467.866806530008
  },
  {
    "type": "mouseMovement",
    "timestamp": "2024-08-20T00:48:30.930Z",
    "totalMouseMovement": 7469.281020092381
  },
  {
    "type": "mouseMovement",
    "timestamp": "2024-08-20T00:48:30.947Z",
    "totalMouseMovement": 7472.443297752549
  },
  {
    "type": "mouseMovement",
    "timestamp": "2024-08-20T00:48:30.963Z",
    "totalMouseMovement": 7475.271724877295
  },
  {
    "type": "mouseMovement",
    "timestamp": "2024-08-20T00:48:30.980Z",
    "totalMouseMovement": 7477.507792854795
  },
  {
    "type": "mouseMovement",
    "timestamp": "2024-08-20T00:48:30.999Z",
    "totalMouseMovement": 7478.507792854795
  },
  {
    "type": "mouseMovement",
    "timestamp": "2024-08-20T00:48:31.013Z",
    "totalMouseMovement": 7480.7438608322955
  },
  {
    "type": "mouseMovement",
    "timestamp": "2024-08-20T00:48:31.030Z",
    "totalMouseMovement": 7482.7438608322955
  },
  {
    "type": "mouseMovement",
    "timestamp": "2024-08-20T00:48:31.059Z",
    "totalMouseMovement": 7483.7438608322955
  },
  {
    "type": "mousewheel",
    "timestamp": "2024-08-20T00:48:31.675Z",
    "deltaY": 100
  },
  {
    "type": "mousewheel",
    "timestamp": "2024-08-20T00:48:31.714Z",
    "deltaY": 100
  },
  {
    "type": "mousewheel",
    "timestamp": "2024-08-20T00:48:31.763Z",
    "deltaY": 100
  },
  {
    "type": "mousewheel",
    "timestamp": "2024-08-20T00:48:31.971Z",
    "deltaY": 100
  },
  {
    "type": "mousewheel",
    "timestamp": "2024-08-20T00:48:31.997Z",
    "deltaY": 100
  },
  {
    "type": "mousewheel",
    "timestamp": "2024-08-20T00:48:32.013Z",
    "deltaY": 100
  },
  {
    "type": "mousewheel",
    "timestamp": "2024-08-20T00:48:32.030Z",
    "deltaY": 100
  },
  {
    "type": "mousewheel",
    "timestamp": "2024-08-20T00:48:32.249Z",
    "deltaY": 100
  },
  {
    "type": "mousewheel",
    "timestamp": "2024-08-20T00:48:32.263Z",
    "deltaY": 100
  },
  {
    "type": "mousewheel",
    "timestamp": "2024-08-20T00:48:32.279Z",
    "deltaY": 100
  },
  {
    "type": "scroll",
    "timestamp": "2024-08-20T00:48:32.787Z",
    "deltaY": 100
  },
  {
    "type": "mouseMovement",
    "timestamp": "2024-08-20T00:48:32.862Z",
    "totalMouseMovement": 7484.7438608322955
  },
  {
    "type": "mouseMovement",
    "timestamp": "2024-08-20T00:48:32.878Z",
    "totalMouseMovement": 7487.9061384924635
  },
  {
    "type": "mouseMovement",
    "timestamp": "2024-08-20T00:48:32.895Z",
    "totalMouseMovement": 7492.9061384924635
  },
  {
    "type": "mouseMovement",
    "timestamp": "2024-08-20T00:48:32.913Z",
    "totalMouseMovement": 7502.805633429075
  },
  {
    "type": "mouseMovement",
    "timestamp": "2024-08-20T00:48:32.930Z",
    "totalMouseMovement": 7518.617021729917
  },
  {
    "type": "mouseMovement",
    "timestamp": "2024-08-20T00:48:32.946Z",
    "totalMouseMovement": 7524.273875979409
  },
  {
    "type": "mouseMovement",
    "timestamp": "2024-08-20T00:48:32.963Z",
    "totalMouseMovement": 7535.6756302304
  },
  {
    "type": "mouseMovement",
    "timestamp": "2024-08-20T00:48:32.979Z",
    "totalMouseMovement": 7544.277955497443
  },
  {
    "type": "mouseMovement",
    "timestamp": "2024-08-20T00:48:32.995Z",
    "totalMouseMovement": 7556.319550076236
  },
  {
    "type": "mouseMovement",
    "timestamp": "2024-08-20T00:48:33.012Z",
    "totalMouseMovement": 7572.7207695430925
  },
  {
    "type": "mouseMovement",
    "timestamp": "2024-08-20T00:48:33.028Z",
    "totalMouseMovement": 7583.537423369485
  },
  {
    "type": "mouseMovement",
    "timestamp": "2024-08-20T00:48:33.045Z",
    "totalMouseMovement": 7593.537423369485
  },
  {
    "type": "mouseMovement",
    "timestamp": "2024-08-20T00:48:33.061Z",
    "totalMouseMovement": 7600.748525920412
  },
  {
    "type": "mouseMovement",
    "timestamp": "2024-08-20T00:48:33.078Z",
    "totalMouseMovement": 7605.220661875412
  },
  {
    "type": "mouseMovement",
    "timestamp": "2024-08-20T00:48:33.095Z",
    "totalMouseMovement": 7608.826213150875
  },
  {
    "type": "mouseMovement",
    "timestamp": "2024-08-20T00:48:33.112Z",
    "totalMouseMovement": 7612.949318776493
  },
  {
    "type": "mouseMovement",
    "timestamp": "2024-08-20T00:48:33.129Z",
    "totalMouseMovement": 7616.111596436661
  },
  {
    "type": "mouseMovement",
    "timestamp": "2024-08-20T00:48:33.145Z",
    "totalMouseMovement": 7618.111596436661
  },
  {
    "type": "mouseMovement",
    "timestamp": "2024-08-20T00:48:33.162Z",
    "totalMouseMovement": 7621.111596436661
  },
  {
    "type": "mouseMovement",
    "timestamp": "2024-08-20T00:48:33.180Z",
    "totalMouseMovement": 7625.58373239166
  },
  {
    "type": "mouseMovement",
    "timestamp": "2024-08-20T00:48:33.195Z",
    "totalMouseMovement": 7626.58373239166
  },
  {
    "type": "mouseMovement",
    "timestamp": "2024-08-20T00:48:33.212Z",
    "totalMouseMovement": 7628.58373239166
  },
  {
    "type": "mouseMovement",
    "timestamp": "2024-08-20T00:48:33.229Z",
    "totalMouseMovement": 7631.58373239166
  },
  {
    "type": "mouseMovement",
    "timestamp": "2024-08-20T00:48:33.246Z",
    "totalMouseMovement": 7633.58373239166
  },
  {
    "type": "mouseMovement",
    "timestamp": "2024-08-20T00:48:33.261Z",
    "totalMouseMovement": 7636.58373239166
  },
  {
    "type": "mouseMovement",
    "timestamp": "2024-08-20T00:48:33.278Z",
    "totalMouseMovement": 7639.746010051828
  },
  {
    "type": "mouseMovement",
    "timestamp": "2024-08-20T00:48:33.295Z",
    "totalMouseMovement": 7641.746010051828
  },
  {
    "type": "mouseMovement",
    "timestamp": "2024-08-20T00:48:33.607Z",
    "totalMouseMovement": 7642.746010051828
  },
  {
    "type": "mouseMovement",
    "timestamp": "2024-08-20T00:48:33.623Z",
    "totalMouseMovement": 7643.746010051828
  },
  {
    "type": "mouseMovement",
    "timestamp": "2024-08-20T00:48:33.627Z",
    "totalMouseMovement": 7644.746010051828
  },
  {
    "type": "mouseMovement",
    "timestamp": "2024-08-20T00:48:33.644Z",
    "totalMouseMovement": 7646.9820780293285
  },
  {
    "type": "mouseMovement",
    "timestamp": "2024-08-20T00:48:33.661Z",
    "totalMouseMovement": 7648.9820780293285
  },
  {
    "type": "mouseMovement",
    "timestamp": "2024-08-20T00:48:33.677Z",
    "totalMouseMovement": 7649.9820780293285
  },
  {
    "type": "mouseMovement",
    "timestamp": "2024-08-20T00:48:33.695Z",
    "totalMouseMovement": 7651.396291591702
  },
  {
    "type": "mouseMovement",
    "timestamp": "2024-08-20T00:48:33.711Z",
    "totalMouseMovement": 7652.810505154075
  }
]